{
"meta":{"test_sets":[],"test_metrics":[],"learn_metrics":[{"best_value":"Min","name":"RMSE"}],"launch_mode":"Train","parameters":"","iteration_count":1000,"learn_sets":["learn"],"name":"experiment"},
"iterations":[
{"learn":[14.61268541],"iteration":0,"passed_time":0.2461911472,"remaining_time":245.9449561},
{"learn":[14.23196558],"iteration":1,"passed_time":0.2483779519,"remaining_time":123.940598},
{"learn":[13.86674177],"iteration":2,"passed_time":0.2562985123,"remaining_time":85.17653892},
{"learn":[13.49946468],"iteration":3,"passed_time":0.2628043706,"remaining_time":65.43828828},
{"learn":[13.16661202],"iteration":4,"passed_time":0.2658552534,"remaining_time":52.90519543},
{"learn":[12.85632158],"iteration":5,"passed_time":0.3641616875,"remaining_time":60.3294529},
{"learn":[12.56784336],"iteration":6,"passed_time":0.4389131669,"remaining_time":62.26296782},
{"learn":[12.31617801],"iteration":7,"passed_time":0.4772308231,"remaining_time":59.17662206},
{"learn":[12.01509946],"iteration":8,"passed_time":0.5023868577,"remaining_time":55.3183751},
{"learn":[11.71512571],"iteration":9,"passed_time":0.5059343078,"remaining_time":50.08749647},
{"learn":[11.43264457],"iteration":10,"passed_time":0.5182721251,"remaining_time":46.59737561},
{"learn":[11.17973129],"iteration":11,"passed_time":0.5399355965,"remaining_time":44.45469745},
{"learn":[10.93746433],"iteration":12,"passed_time":0.7182582883,"remaining_time":54.53237928},
{"learn":[10.69387075],"iteration":13,"passed_time":0.7277219998,"remaining_time":51.25242085},
{"learn":[10.4615922],"iteration":14,"passed_time":0.7512629125,"remaining_time":49.33293126},
{"learn":[10.2299235],"iteration":15,"passed_time":0.7830722363,"remaining_time":48.15894253},
{"learn":[10.01419731],"iteration":16,"passed_time":0.8259346001,"remaining_time":47.75845364},
{"learn":[9.795856918],"iteration":17,"passed_time":0.834414766,"remaining_time":45.52196112},
{"learn":[9.60040151],"iteration":18,"passed_time":0.8394465457,"remaining_time":43.3419506},
{"learn":[9.418664989],"iteration":19,"passed_time":0.8583957499,"remaining_time":42.06139174},
{"learn":[9.249278645],"iteration":20,"passed_time":0.865753908,"remaining_time":40.36062266},
{"learn":[9.090113396],"iteration":21,"passed_time":0.8748734279,"remaining_time":38.89210057},
{"learn":[8.909548708],"iteration":22,"passed_time":0.884872673,"remaining_time":37.58785224},
{"learn":[8.740140208],"iteration":23,"passed_time":0.8940729687,"remaining_time":36.35896739},
{"learn":[8.59377682],"iteration":24,"passed_time":0.9011455658,"remaining_time":35.14467707},
{"learn":[8.453885414],"iteration":25,"passed_time":0.9090693208,"remaining_time":34.05513532},
{"learn":[8.317732234],"iteration":26,"passed_time":0.943037007,"remaining_time":33.98425955},
{"learn":[8.180896085],"iteration":27,"passed_time":0.9462383016,"remaining_time":32.84798676},
{"learn":[8.053220863],"iteration":28,"passed_time":1.007148079,"remaining_time":33.72209601},
{"learn":[7.924234474],"iteration":29,"passed_time":1.009801106,"remaining_time":32.65023576},
{"learn":[7.818879511],"iteration":30,"passed_time":1.014394167,"remaining_time":31.70799832},
{"learn":[7.719346395],"iteration":31,"passed_time":1.02124752,"remaining_time":30.89273747},
{"learn":[7.624163594],"iteration":32,"passed_time":1.032812929,"remaining_time":30.26454857},
{"learn":[7.524952543],"iteration":33,"passed_time":1.035876194,"remaining_time":29.43107068},
{"learn":[7.424464745],"iteration":34,"passed_time":1.039380038,"remaining_time":28.65719249},
{"learn":[7.327482321],"iteration":35,"passed_time":1.043360908,"remaining_time":27.93888653},
{"learn":[7.238666841],"iteration":36,"passed_time":1.045830252,"remaining_time":27.21985224},
{"learn":[7.158842395],"iteration":37,"passed_time":1.069740433,"remaining_time":27.08132361},
{"learn":[7.074348246],"iteration":38,"passed_time":1.072367471,"remaining_time":26.42423434},
{"learn":[6.992269093],"iteration":39,"passed_time":1.079886212,"remaining_time":25.91726908},
{"learn":[6.925219745],"iteration":40,"passed_time":1.094152466,"remaining_time":25.59249304},
{"learn":[6.86013671],"iteration":41,"passed_time":1.100219631,"remaining_time":25.09548587},
{"learn":[6.786739622],"iteration":42,"passed_time":1.106673162,"remaining_time":24.629912},
{"learn":[6.73057926],"iteration":43,"passed_time":1.111370535,"remaining_time":24.14705072},
{"learn":[6.666356486],"iteration":44,"passed_time":1.139432404,"remaining_time":24.18128768},
{"learn":[6.606182832],"iteration":45,"passed_time":1.168025103,"remaining_time":24.22382497},
{"learn":[6.547854615],"iteration":46,"passed_time":1.170924441,"remaining_time":23.74236153},
{"learn":[6.49240675],"iteration":47,"passed_time":1.175532095,"remaining_time":23.31471988},
{"learn":[6.431317261],"iteration":48,"passed_time":1.178325544,"remaining_time":22.86913453},
{"learn":[6.377586395],"iteration":49,"passed_time":1.180994592,"remaining_time":22.43889724},
{"learn":[6.327558015],"iteration":50,"passed_time":1.184032046,"remaining_time":22.03228259},
{"learn":[6.282040317],"iteration":51,"passed_time":1.186923253,"remaining_time":21.63852392},
{"learn":[6.237655841],"iteration":52,"passed_time":1.189612305,"remaining_time":21.25590288},
{"learn":[6.192792003],"iteration":53,"passed_time":1.192619974,"remaining_time":20.8929351},
{"learn":[6.150579347],"iteration":54,"passed_time":1.19531901,"remaining_time":20.5377539},
{"learn":[6.115693845],"iteration":55,"passed_time":1.1997908,"remaining_time":20.22504491},
{"learn":[6.078780782],"iteration":56,"passed_time":1.202336414,"remaining_time":19.89128488},
{"learn":[6.045146957],"iteration":57,"passed_time":1.204588895,"remaining_time":19.56418516},
{"learn":[6.008080327],"iteration":58,"passed_time":1.206316432,"remaining_time":19.23972479},
{"learn":[5.977575734],"iteration":59,"passed_time":1.208544617,"remaining_time":18.93386566},
{"learn":[5.948036502],"iteration":60,"passed_time":1.21200858,"remaining_time":18.65698454},
{"learn":[5.914888282],"iteration":61,"passed_time":1.215168806,"remaining_time":18.38432807},
{"learn":[5.884957796],"iteration":62,"passed_time":1.217851566,"remaining_time":18.11312567},
{"learn":[5.849539885],"iteration":63,"passed_time":1.22484256,"remaining_time":17.91332243},
{"learn":[5.821387627],"iteration":64,"passed_time":1.227506313,"remaining_time":17.65720619},
{"learn":[5.797012279],"iteration":65,"passed_time":1.230448166,"remaining_time":17.41270586},
{"learn":[5.768685095],"iteration":66,"passed_time":1.232843986,"remaining_time":17.16781252},
{"learn":[5.755484587],"iteration":67,"passed_time":1.233902802,"remaining_time":16.91172664},
{"learn":[5.731887055],"iteration":68,"passed_time":1.23576182,"remaining_time":16.67382978},
{"learn":[5.707148487],"iteration":69,"passed_time":1.239418361,"remaining_time":16.46655823},
{"learn":[5.685365039],"iteration":70,"passed_time":1.246158996,"remaining_time":16.30537616},
{"learn":[5.663541834],"iteration":71,"passed_time":1.249163667,"remaining_time":16.10033171},
{"learn":[5.638108797],"iteration":72,"passed_time":1.252302807,"remaining_time":15.90253017},
{"learn":[5.619204893],"iteration":73,"passed_time":1.254465421,"remaining_time":15.69776999},
{"learn":[5.598472793],"iteration":74,"passed_time":1.258007274,"remaining_time":15.51542305},
{"learn":[5.577007075],"iteration":75,"passed_time":1.260393672,"remaining_time":15.3237336},
{"learn":[5.562637084],"iteration":76,"passed_time":1.263276108,"remaining_time":15.14290711},
{"learn":[5.54729991],"iteration":77,"passed_time":1.266289576,"remaining_time":14.96819217},
{"learn":[5.530737623],"iteration":78,"passed_time":1.269709024,"remaining_time":14.8025571},
{"learn":[5.513704873],"iteration":79,"passed_time":1.272372062,"remaining_time":14.63227871},
{"learn":[5.501575529],"iteration":80,"passed_time":1.275441436,"remaining_time":14.47074913},
{"learn":[5.484080734],"iteration":81,"passed_time":1.277477278,"remaining_time":14.30151391},
{"learn":[5.472178894],"iteration":82,"passed_time":1.279271872,"remaining_time":14.13364225},
{"learn":[5.458923342],"iteration":83,"passed_time":1.281183655,"remaining_time":13.97100271},
{"learn":[5.451382371],"iteration":84,"passed_time":1.282312199,"remaining_time":13.80371367},
{"learn":[5.441410748],"iteration":85,"passed_time":1.284439925,"remaining_time":13.65090804},
{"learn":[5.434047468],"iteration":86,"passed_time":1.285612165,"remaining_time":13.49153916},
{"learn":[5.422107497],"iteration":87,"passed_time":1.287329571,"remaining_time":13.34141555},
{"learn":[5.40731265],"iteration":88,"passed_time":1.289024843,"remaining_time":13.19440036},
{"learn":[5.396360181],"iteration":89,"passed_time":1.291617077,"remaining_time":13.05968378},
{"learn":[5.383793239],"iteration":90,"passed_time":1.295726662,"remaining_time":12.94302786},
{"learn":[5.369605034],"iteration":91,"passed_time":1.2977853,"remaining_time":12.80857666},
{"learn":[5.357467333],"iteration":92,"passed_time":1.299482794,"remaining_time":12.67345048},
{"learn":[5.341109968],"iteration":93,"passed_time":1.303221265,"remaining_time":12.56083474},
{"learn":[5.330529276],"iteration":94,"passed_time":1.305325172,"remaining_time":12.43493979},
{"learn":[5.319862075],"iteration":95,"passed_time":1.307237728,"remaining_time":12.30982193},
{"learn":[5.313052243],"iteration":96,"passed_time":1.310581565,"remaining_time":12.20056859},
{"learn":[5.299677207],"iteration":97,"passed_time":1.313255797,"remaining_time":12.08731356},
{"learn":[5.287546698],"iteration":98,"passed_time":1.315546266,"remaining_time":11.97279986},
{"learn":[5.279803754],"iteration":99,"passed_time":1.317386679,"remaining_time":11.85648011},
{"learn":[5.272254612],"iteration":100,"passed_time":1.320621668,"remaining_time":11.75484039},
{"learn":[5.268813888],"iteration":101,"passed_time":1.322267441,"remaining_time":11.64113885},
{"learn":[5.258113767],"iteration":102,"passed_time":1.324289148,"remaining_time":11.53288704},
{"learn":[5.251018576],"iteration":103,"passed_time":1.327438453,"remaining_time":11.43639282},
{"learn":[5.24171237],"iteration":104,"passed_time":1.333496345,"remaining_time":11.36646885},
{"learn":[5.233984943],"iteration":105,"passed_time":1.33543063,"remaining_time":11.26297154},
{"learn":[5.226240449],"iteration":106,"passed_time":1.339412873,"remaining_time":11.17846444},
{"learn":[5.220541644],"iteration":107,"passed_time":1.341150965,"remaining_time":11.07691353},
{"learn":[5.211712096],"iteration":108,"passed_time":1.342650454,"remaining_time":10.97524362},
{"learn":[5.203388597],"iteration":109,"passed_time":1.344198651,"remaining_time":10.87578908},
{"learn":[5.196026544],"iteration":110,"passed_time":1.346940612,"remaining_time":10.7876595},
{"learn":[5.188716772],"iteration":111,"passed_time":1.349048771,"remaining_time":10.69602954},
{"learn":[5.182163132],"iteration":112,"passed_time":1.350846708,"remaining_time":10.60354894},
{"learn":[5.17764747],"iteration":113,"passed_time":1.352408384,"remaining_time":10.51082306},
{"learn":[5.170548056],"iteration":114,"passed_time":1.354012501,"remaining_time":10.42000925},
{"learn":[5.165901827],"iteration":115,"passed_time":1.356731136,"remaining_time":10.33922693},
{"learn":[5.160333668],"iteration":116,"passed_time":1.358796436,"remaining_time":10.25484831},
{"learn":[5.148953243],"iteration":117,"passed_time":1.360431086,"remaining_time":10.16864591},
{"learn":[5.144729126],"iteration":118,"passed_time":1.361781302,"remaining_time":10.08175905},
{"learn":[5.139939946],"iteration":119,"passed_time":1.364122854,"remaining_time":10.0035676},
{"learn":[5.132898872],"iteration":120,"passed_time":1.369043271,"remaining_time":9.945363928},
{"learn":[5.129073077],"iteration":121,"passed_time":1.371824797,"remaining_time":9.87264075},
{"learn":[5.127123916],"iteration":122,"passed_time":1.374107969,"remaining_time":9.797501537},
{"learn":[5.121282057],"iteration":123,"passed_time":1.376922195,"remaining_time":9.727289056},
{"learn":[5.114489821],"iteration":124,"passed_time":1.379123846,"remaining_time":9.653866923},
{"learn":[5.107777291],"iteration":125,"passed_time":1.38423792,"remaining_time":9.601777321},
{"learn":[5.103518754],"iteration":126,"passed_time":1.386956251,"remaining_time":9.533959115},
{"learn":[5.101133351],"iteration":127,"passed_time":1.388477883,"remaining_time":9.459005581},
{"learn":[5.096462705],"iteration":128,"passed_time":1.390620236,"remaining_time":9.389381596},
{"learn":[5.08562082],"iteration":129,"passed_time":1.39624243,"remaining_time":9.344083954},
{"learn":[5.080483682],"iteration":130,"passed_time":1.398521823,"remaining_time":9.277217286},
{"learn":[5.07437499],"iteration":131,"passed_time":1.402033996,"remaining_time":9.219435671},
{"learn":[5.070683732],"iteration":132,"passed_time":1.405483007,"remaining_time":9.1620584},
{"learn":[5.06432037],"iteration":133,"passed_time":1.407541834,"remaining_time":9.096501704},
{"learn":[5.057436484],"iteration":134,"passed_time":1.412338912,"remaining_time":9.049430803},
{"learn":[5.053254656],"iteration":135,"passed_time":1.418141956,"remaining_time":9.009372427},
{"learn":[5.04801663],"iteration":136,"passed_time":1.45037796,"remaining_time":9.136322479},
{"learn":[5.045680836],"iteration":137,"passed_time":1.45227282,"remaining_time":9.071443266},
{"learn":[5.041857933],"iteration":138,"passed_time":1.455119886,"remaining_time":9.013368504},
{"learn":[5.035264888],"iteration":139,"passed_time":1.457264868,"remaining_time":8.951769904},
{"learn":[5.028771948],"iteration":140,"passed_time":1.459689119,"remaining_time":8.892715978},
{"learn":[5.024912247],"iteration":141,"passed_time":1.461789174,"remaining_time":8.832500783},
{"learn":[5.02239068],"iteration":142,"passed_time":1.463667854,"remaining_time":8.771771687},
{"learn":[5.017110572],"iteration":143,"passed_time":1.467884061,"remaining_time":8.725755253},
{"learn":[5.010707886],"iteration":144,"passed_time":1.470414297,"remaining_time":8.670373961},
{"learn":[5.004389868],"iteration":145,"passed_time":1.472792823,"remaining_time":8.61482925},
{"learn":[4.997628683],"iteration":146,"passed_time":1.474958955,"remaining_time":8.558775434},
{"learn":[4.991497851],"iteration":147,"passed_time":1.477953208,"remaining_time":8.508217114},
{"learn":[4.988345253],"iteration":148,"passed_time":1.479846605,"remaining_time":8.452009805},
{"learn":[4.98460423],"iteration":149,"passed_time":1.482393251,"remaining_time":8.400228422},
{"learn":[4.982441783],"iteration":150,"passed_time":1.485640073,"remaining_time":8.353035909},
{"learn":[4.977461771],"iteration":151,"passed_time":1.487592976,"remaining_time":8.299202917},
{"learn":[4.973601586],"iteration":152,"passed_time":1.489121825,"remaining_time":8.243700563},
{"learn":[4.968328804],"iteration":153,"passed_time":1.490646551,"remaining_time":8.18887651},
{"learn":[4.9640736],"iteration":154,"passed_time":1.492184155,"remaining_time":8.134810391},
{"learn":[4.960865882],"iteration":155,"passed_time":1.495552956,"remaining_time":8.091324967},
{"learn":[4.957014156],"iteration":156,"passed_time":1.497439524,"remaining_time":8.040391839},
{"learn":[4.952244852],"iteration":157,"passed_time":1.498927645,"remaining_time":7.987956182},
{"learn":[4.949695675],"iteration":158,"passed_time":1.50053734,"remaining_time":7.936804423},
{"learn":[4.946584698],"iteration":159,"passed_time":1.503164284,"remaining_time":7.89161249},
{"learn":[4.940192834],"iteration":160,"passed_time":1.505225825,"remaining_time":7.8440029},
{"learn":[4.936727994],"iteration":161,"passed_time":1.506644346,"remaining_time":7.793629393},
{"learn":[4.932342063],"iteration":162,"passed_time":1.508142744,"remaining_time":7.74426673},
{"learn":[4.925830838],"iteration":163,"passed_time":1.51302973,"remaining_time":7.712761308},
{"learn":[4.922571773],"iteration":164,"passed_time":1.515350731,"remaining_time":7.668593095},
{"learn":[4.918395814],"iteration":165,"passed_time":1.517635652,"remaining_time":7.624747792},
{"learn":[4.911142452],"iteration":166,"passed_time":1.519214423,"remaining_time":7.577877932},
{"learn":[4.908276131],"iteration":167,"passed_time":1.521650881,"remaining_time":7.535794841},
{"learn":[4.904584645],"iteration":168,"passed_time":1.524074772,"remaining_time":7.494119145},
{"learn":[4.89795517],"iteration":169,"passed_time":1.526268275,"remaining_time":7.451780402},
{"learn":[4.895556491],"iteration":170,"passed_time":1.528350919,"remaining_time":7.409373753},
{"learn":[4.890591233],"iteration":171,"passed_time":1.532029019,"remaining_time":7.375116438},
{"learn":[4.884629277],"iteration":172,"passed_time":1.53358853,"remaining_time":7.331085052},
{"learn":[4.880550786],"iteration":173,"passed_time":1.535041972,"remaining_time":7.287038325},
{"learn":[4.876384842],"iteration":174,"passed_time":1.536554742,"remaining_time":7.243758068},
{"learn":[4.872638238],"iteration":175,"passed_time":1.539358236,"remaining_time":7.206995377},
{"learn":[4.869137118],"iteration":176,"passed_time":1.541412569,"remaining_time":7.167133019},
{"learn":[4.863587157],"iteration":177,"passed_time":1.542910089,"remaining_time":7.125124121},
{"learn":[4.858028614],"iteration":178,"passed_time":1.544463297,"remaining_time":7.083823277},
{"learn":[4.853838176],"iteration":179,"passed_time":1.545875155,"remaining_time":7.042320149},
{"learn":[4.853462329],"iteration":180,"passed_time":1.546616044,"remaining_time":6.998223976},
{"learn":[4.851573196],"iteration":181,"passed_time":1.549137179,"remaining_time":6.962605562},
{"learn":[4.848442087],"iteration":182,"passed_time":1.551069055,"remaining_time":6.924718132},
{"learn":[4.845547104],"iteration":183,"passed_time":1.553651081,"remaining_time":6.890104793},
{"learn":[4.839868817],"iteration":184,"passed_time":1.555331919,"remaining_time":6.851867641},
{"learn":[4.836336958],"iteration":185,"passed_time":1.55838028,"remaining_time":6.820008322},
{"learn":[4.831124789],"iteration":186,"passed_time":1.560067385,"remaining_time":6.782538953},
{"learn":[4.827407333],"iteration":187,"passed_time":1.56158849,"remaining_time":6.744733266},
{"learn":[4.824088918],"iteration":188,"passed_time":1.563027627,"remaining_time":6.706959819},
{"learn":[4.820934539],"iteration":189,"passed_time":1.564460959,"remaining_time":6.669544088},
{"learn":[4.816975227],"iteration":190,"passed_time":1.566660433,"remaining_time":6.635750211},
{"learn":[4.812340486],"iteration":191,"passed_time":1.569081029,"remaining_time":6.603215996},
{"learn":[4.806402747],"iteration":192,"passed_time":1.570595426,"remaining_time":6.567204708},
{"learn":[4.801521788],"iteration":193,"passed_time":1.572098421,"remaining_time":6.531501685},
{"learn":[4.797601172],"iteration":194,"passed_time":1.574877241,"remaining_time":6.501416304},
{"learn":[4.792694629],"iteration":195,"passed_time":1.576894446,"remaining_time":6.468485379},
{"learn":[4.789794613],"iteration":196,"passed_time":1.578369097,"remaining_time":6.433656775},
{"learn":[4.785367055],"iteration":197,"passed_time":1.580399012,"remaining_time":6.401414179},
{"learn":[4.780376856],"iteration":198,"passed_time":1.584851555,"remaining_time":6.37922661},
{"learn":[4.776691261],"iteration":199,"passed_time":1.586457896,"remaining_time":6.345831584},
{"learn":[4.773470753],"iteration":200,"passed_time":1.587931398,"remaining_time":6.31222481},
{"learn":[4.77207327],"iteration":201,"passed_time":1.589342828,"remaining_time":6.278690975},
{"learn":[4.767347177],"iteration":202,"passed_time":1.591061402,"remaining_time":6.246679493},
{"learn":[4.763983068],"iteration":203,"passed_time":1.594076944,"remaining_time":6.220025721},
{"learn":[4.761588849],"iteration":204,"passed_time":1.596687392,"remaining_time":6.192031593},
{"learn":[4.758558086],"iteration":205,"passed_time":1.598322424,"remaining_time":6.160524294},
{"learn":[4.753678804],"iteration":206,"passed_time":1.599869646,"remaining_time":6.128969222},
{"learn":[4.746510889],"iteration":207,"passed_time":1.602448533,"remaining_time":6.101630953},
{"learn":[4.744840601],"iteration":208,"passed_time":1.604212483,"remaining_time":6.071445331},
{"learn":[4.741702222],"iteration":209,"passed_time":1.605721134,"remaining_time":6.04056998},
{"learn":[4.739352853],"iteration":210,"passed_time":1.607240057,"remaining_time":6.010011397},
{"learn":[4.735539287],"iteration":211,"passed_time":1.608628042,"remaining_time":5.979240082},
{"learn":[4.730726751],"iteration":212,"passed_time":1.612331908,"remaining_time":5.957301464},
{"learn":[4.726416092],"iteration":213,"passed_time":1.614127975,"remaining_time":5.928526113},
{"learn":[4.721293082],"iteration":214,"passed_time":1.615911312,"remaining_time":5.899955256},
{"learn":[4.718443695],"iteration":215,"passed_time":1.61746115,"remaining_time":5.870784914},
{"learn":[4.711627962],"iteration":216,"passed_time":1.62089736,"remaining_time":5.848675729},
{"learn":[4.709790764],"iteration":217,"passed_time":1.622740526,"remaining_time":5.821023355},
{"learn":[4.706913073],"iteration":218,"passed_time":1.626712039,"remaining_time":5.801196814},
{"learn":[4.703846389],"iteration":219,"passed_time":1.630037509,"remaining_time":5.779223897},
{"learn":[4.701001135],"iteration":220,"passed_time":1.632617227,"remaining_time":5.754791041},
{"learn":[4.700380864],"iteration":221,"passed_time":1.634136561,"remaining_time":5.726838938},
{"learn":[4.695837486],"iteration":222,"passed_time":1.63562507,"remaining_time":5.699016499},
{"learn":[4.691242996],"iteration":223,"passed_time":1.637905534,"remaining_time":5.674172741},
{"learn":[4.690284609],"iteration":224,"passed_time":1.640049166,"remaining_time":5.649058239},
{"learn":[4.68827119],"iteration":225,"passed_time":1.641503516,"remaining_time":5.621786379},
{"learn":[4.686922425],"iteration":226,"passed_time":1.642984841,"remaining_time":5.59483384},
{"learn":[4.686085874],"iteration":227,"passed_time":1.644337158,"remaining_time":5.567667922},
{"learn":[4.683230741],"iteration":228,"passed_time":1.645913816,"remaining_time":5.541482759},
{"learn":[4.6773487],"iteration":229,"passed_time":1.648633729,"remaining_time":5.519339005},
{"learn":[4.671462906],"iteration":230,"passed_time":1.650599052,"remaining_time":5.49485139},
{"learn":[4.664799601],"iteration":231,"passed_time":1.65289306,"remaining_time":5.47164599},
{"learn":[4.660979386],"iteration":232,"passed_time":1.65742666,"remaining_time":5.45599248},
{"learn":[4.656281279],"iteration":233,"passed_time":1.661546547,"remaining_time":5.439079721},
{"learn":[4.651997094],"iteration":234,"passed_time":1.663424255,"remaining_time":5.41497683},
{"learn":[4.650151977],"iteration":235,"passed_time":1.66623691,"remaining_time":5.394088979},
{"learn":[4.648478046],"iteration":236,"passed_time":1.668340161,"remaining_time":5.371069802},
{"learn":[4.646364602],"iteration":237,"passed_time":1.669945618,"remaining_time":5.34663261},
{"learn":[4.642635873],"iteration":238,"passed_time":1.671511851,"remaining_time":5.322261586},
{"learn":[4.640860821],"iteration":239,"passed_time":1.673616951,"remaining_time":5.299787012},
{"learn":[4.639446822],"iteration":240,"passed_time":1.675640309,"remaining_time":5.277224043},
{"learn":[4.637120072],"iteration":241,"passed_time":1.678110754,"remaining_time":5.256231204},
{"learn":[4.633769267],"iteration":242,"passed_time":1.683952834,"remaining_time":5.245894219},
{"learn":[4.630491517],"iteration":243,"passed_time":1.688077727,"remaining_time":5.230273612},
{"learn":[4.627813333],"iteration":244,"passed_time":1.690418694,"remaining_time":5.209249444},
{"learn":[4.622496304],"iteration":245,"passed_time":1.696782697,"remaining_time":5.200707941},
{"learn":[4.618979301],"iteration":246,"passed_time":1.701821654,"remaining_time":5.188144556},
{"learn":[4.616563458],"iteration":247,"passed_time":1.708661691,"remaining_time":5.181103192},
{"learn":[4.614759385],"iteration":248,"passed_time":1.713198414,"remaining_time":5.167116501},
{"learn":[4.61251363],"iteration":249,"passed_time":1.715628477,"remaining_time":5.146885432},
{"learn":[4.608796693],"iteration":250,"passed_time":1.72533894,"remaining_time":5.148521378},
{"learn":[4.60847774],"iteration":251,"passed_time":1.728619187,"remaining_time":5.130980763},
{"learn":[4.605195659],"iteration":252,"passed_time":1.733234098,"remaining_time":5.117493562},
{"learn":[4.60103766],"iteration":253,"passed_time":1.736805607,"remaining_time":5.101011744},
{"learn":[4.599325598],"iteration":254,"passed_time":1.742420156,"remaining_time":5.090600062},
{"learn":[4.597012808],"iteration":255,"passed_time":1.746762365,"remaining_time":5.076528122},
{"learn":[4.594161533],"iteration":256,"passed_time":1.753799127,"remaining_time":5.070321989},
{"learn":[4.592197259],"iteration":257,"passed_time":1.758839766,"remaining_time":5.05836863},
{"learn":[4.58952828],"iteration":258,"passed_time":1.760811048,"remaining_time":5.037687208},
{"learn":[4.585816572],"iteration":259,"passed_time":1.762506499,"remaining_time":5.016364651},
{"learn":[4.582934052],"iteration":260,"passed_time":1.765849576,"remaining_time":4.999857612},
{"learn":[4.582234842],"iteration":261,"passed_time":1.777486383,"remaining_time":5.006812789},
{"learn":[4.57571562],"iteration":262,"passed_time":1.78578124,"remaining_time":5.004261497},
{"learn":[4.571197349],"iteration":263,"passed_time":1.7880517,"remaining_time":4.984871405},
{"learn":[4.56723703],"iteration":264,"passed_time":1.79110631,"remaining_time":4.967785427},
{"learn":[4.560335567],"iteration":265,"passed_time":1.797031517,"remaining_time":4.958726065},
{"learn":[4.554709345],"iteration":266,"passed_time":1.799706706,"remaining_time":4.940767849},
{"learn":[4.552806306],"iteration":267,"passed_time":1.802991599,"remaining_time":4.924588994},
{"learn":[4.550766241],"iteration":268,"passed_time":1.805518487,"remaining_time":4.906446148},
{"learn":[4.549216045],"iteration":269,"passed_time":1.807263581,"remaining_time":4.886305236},
{"learn":[4.547687452],"iteration":270,"passed_time":1.809310959,"remaining_time":4.867113245},
{"learn":[4.545642435],"iteration":271,"passed_time":1.812246194,"remaining_time":4.850423636},
{"learn":[4.543930359],"iteration":272,"passed_time":1.814333318,"remaining_time":4.831576273},
{"learn":[4.541029943],"iteration":273,"passed_time":1.816224688,"remaining_time":4.812332567},
{"learn":[4.537781449],"iteration":274,"passed_time":1.818593217,"remaining_time":4.794473026},
{"learn":[4.53066128],"iteration":275,"passed_time":1.829496397,"remaining_time":4.799113736},
{"learn":[4.526763956],"iteration":276,"passed_time":1.833782443,"remaining_time":4.786370782},
{"learn":[4.522036004],"iteration":277,"passed_time":1.840164863,"remaining_time":4.779133206},
{"learn":[4.515307629],"iteration":278,"passed_time":1.851022185,"remaining_time":4.783465933},
{"learn":[4.51109143],"iteration":279,"passed_time":1.856032081,"remaining_time":4.772653923},
{"learn":[4.508233494],"iteration":280,"passed_time":1.861756063,"remaining_time":4.763710354},
{"learn":[4.502555629],"iteration":281,"passed_time":1.870327038,"remaining_time":4.762038345},
{"learn":[4.500081355],"iteration":282,"passed_time":1.877008958,"remaining_time":4.755531529},
{"learn":[4.495281743],"iteration":283,"passed_time":1.887711751,"remaining_time":4.759160611},
{"learn":[4.492138869],"iteration":284,"passed_time":1.89635849,"remaining_time":4.757530948},
{"learn":[4.491708261],"iteration":285,"passed_time":1.90093999,"remaining_time":4.745703332},
{"learn":[4.489398865],"iteration":286,"passed_time":1.908408667,"remaining_time":4.741098884},
{"learn":[4.485796373],"iteration":287,"passed_time":1.942029526,"remaining_time":4.801128549},
{"learn":[4.479542205],"iteration":288,"passed_time":1.948053876,"remaining_time":4.792616975},
{"learn":[4.475986993],"iteration":289,"passed_time":1.955171416,"remaining_time":4.786798984},
{"learn":[4.468661855],"iteration":290,"passed_time":1.961509658,"remaining_time":4.779073359},
{"learn":[4.463785664],"iteration":291,"passed_time":1.966182166,"remaining_time":4.767318403},
{"learn":[4.460445831],"iteration":292,"passed_time":1.974905295,"remaining_time":4.765385815},
{"learn":[4.45692492],"iteration":293,"passed_time":1.978049204,"remaining_time":4.750009314},
{"learn":[4.454031688],"iteration":294,"passed_time":1.981898107,"remaining_time":4.73640056},
{"learn":[4.451672391],"iteration":295,"passed_time":1.98546875,"remaining_time":4.722195946},
{"learn":[4.45031553],"iteration":296,"passed_time":1.989704516,"remaining_time":4.709637288},
{"learn":[4.446782666],"iteration":297,"passed_time":1.993028681,"remaining_time":4.694987026},
{"learn":[4.444369689],"iteration":298,"passed_time":1.996594591,"remaining_time":4.680979293},
{"learn":[4.44411683],"iteration":299,"passed_time":2.001857666,"remaining_time":4.671001221},
{"learn":[4.440876943],"iteration":300,"passed_time":2.006653242,"remaining_time":4.659968825},
{"learn":[4.439336453],"iteration":301,"passed_time":2.009954351,"remaining_time":4.645523633},
{"learn":[4.436666901],"iteration":302,"passed_time":2.013421326,"remaining_time":4.631533546},
{"learn":[4.433043336],"iteration":303,"passed_time":2.016567123,"remaining_time":4.616877361},
{"learn":[4.431419305],"iteration":304,"passed_time":2.020364634,"remaining_time":4.603781707},
{"learn":[4.428859646],"iteration":305,"passed_time":2.024477106,"remaining_time":4.591461148},
{"learn":[4.424552441],"iteration":306,"passed_time":2.029105775,"remaining_time":4.580359291},
{"learn":[4.422706391],"iteration":307,"passed_time":2.032382591,"remaining_time":4.566262185},
{"learn":[4.421427994],"iteration":308,"passed_time":2.035656018,"remaining_time":4.552227536},
{"learn":[4.418733158],"iteration":309,"passed_time":2.039674343,"remaining_time":4.539920312},
{"learn":[4.415656941],"iteration":310,"passed_time":2.042610094,"remaining_time":4.525268022},
{"learn":[4.410747417],"iteration":311,"passed_time":2.045350516,"remaining_time":4.510260113},
{"learn":[4.408126521],"iteration":312,"passed_time":2.048683058,"remaining_time":4.496630226},
{"learn":[4.407843853],"iteration":313,"passed_time":2.053218593,"remaining_time":4.485694123},
{"learn":[4.405219398],"iteration":314,"passed_time":2.060848068,"remaining_time":4.481526751},
{"learn":[4.402708465],"iteration":315,"passed_time":2.068206447,"remaining_time":4.476750665},
{"learn":[4.40104971],"iteration":316,"passed_time":2.071141466,"remaining_time":4.462427828},
{"learn":[4.400830038],"iteration":317,"passed_time":2.080286843,"remaining_time":4.461495682},
{"learn":[4.39784288],"iteration":318,"passed_time":2.086706409,"remaining_time":4.454692992},
{"learn":[4.393741845],"iteration":319,"passed_time":2.090054829,"remaining_time":4.441366512},
{"learn":[4.393425936],"iteration":320,"passed_time":2.097558402,"remaining_time":4.436891449},
{"learn":[4.390505974],"iteration":321,"passed_time":2.10316761,"remaining_time":4.428408819},
{"learn":[4.390305136],"iteration":322,"passed_time":2.110083071,"remaining_time":4.422681855},
{"learn":[4.38568203],"iteration":323,"passed_time":2.118459252,"remaining_time":4.419995231},
{"learn":[4.383057135],"iteration":324,"passed_time":2.135017036,"remaining_time":4.434266153},
{"learn":[4.380662684],"iteration":325,"passed_time":2.182717464,"remaining_time":4.512734879},
{"learn":[4.37805727],"iteration":326,"passed_time":2.196203022,"remaining_time":4.520014171},
{"learn":[4.373708319],"iteration":327,"passed_time":2.212394201,"remaining_time":4.53271007},
{"learn":[4.36887921],"iteration":328,"passed_time":2.216431967,"remaining_time":4.520443314},
{"learn":[4.367895929],"iteration":329,"passed_time":2.220191966,"remaining_time":4.507662477},
{"learn":[4.362140573],"iteration":330,"passed_time":2.222613591,"remaining_time":4.492231094},
{"learn":[4.361931924],"iteration":331,"passed_time":2.224853885,"remaining_time":4.476513239},
{"learn":[4.359656377],"iteration":332,"passed_time":2.227128964,"remaining_time":4.460946003},
{"learn":[4.354281355],"iteration":333,"passed_time":2.229160066,"remaining_time":4.444971868},
{"learn":[4.348589447],"iteration":334,"passed_time":2.231748692,"remaining_time":4.430187702},
{"learn":[4.346355698],"iteration":335,"passed_time":2.233520035,"remaining_time":4.413861022},
{"learn":[4.343894047],"iteration":336,"passed_time":2.235247023,"remaining_time":4.397533461},
{"learn":[4.341561356],"iteration":337,"passed_time":2.237013523,"remaining_time":4.381369682},
{"learn":[4.338869061],"iteration":338,"passed_time":2.2396032,"remaining_time":4.366895915},
{"learn":[4.333720063],"iteration":339,"passed_time":2.241597593,"remaining_time":4.351336503},
{"learn":[4.330892223],"iteration":340,"passed_time":2.24340789,"remaining_time":4.335500878},
{"learn":[4.328311474],"iteration":341,"passed_time":2.24548539,"remaining_time":4.320261365},
{"learn":[4.324580133],"iteration":342,"passed_time":2.247962533,"remaining_time":4.305864093},
{"learn":[4.323354432],"iteration":343,"passed_time":2.250153306,"remaining_time":4.290990026},
{"learn":[4.323159553],"iteration":344,"passed_time":2.251775247,"remaining_time":4.275109526},
{"learn":[4.318639682],"iteration":345,"passed_time":2.253425647,"remaining_time":4.25936524},
{"learn":[4.312712208],"iteration":346,"passed_time":2.255233625,"remaining_time":4.243998723},
{"learn":[4.311461062],"iteration":347,"passed_time":2.258109186,"remaining_time":4.230710313},
{"learn":[4.311178356],"iteration":348,"passed_time":2.260280343,"remaining_time":4.216167632},
{"learn":[4.311102505],"iteration":349,"passed_time":2.262238488,"remaining_time":4.201300049},
{"learn":[4.310232308],"iteration":350,"passed_time":2.263646331,"remaining_time":4.185488515},
{"learn":[4.305128197],"iteration":351,"passed_time":2.265950266,"remaining_time":4.171408444},
{"learn":[4.304595496],"iteration":352,"passed_time":2.26733792,"remaining_time":4.155715678},
{"learn":[4.3004992],"iteration":353,"passed_time":2.268736429,"remaining_time":4.14012354},
{"learn":[4.297581524],"iteration":354,"passed_time":2.270107195,"remaining_time":4.124560961},
{"learn":[4.297355825],"iteration":355,"passed_time":2.271374893,"remaining_time":4.108891661},
{"learn":[4.295758715],"iteration":356,"passed_time":2.273077078,"remaining_time":4.094085605},
{"learn":[4.292500657],"iteration":357,"passed_time":2.275443029,"remaining_time":4.080543085},
{"learn":[4.290797586],"iteration":358,"passed_time":2.276916427,"remaining_time":4.065469164},
{"learn":[4.286410608],"iteration":359,"passed_time":2.278365646,"remaining_time":4.050427815},
{"learn":[4.280278245],"iteration":360,"passed_time":2.27973106,"remaining_time":4.035313428},
{"learn":[4.279941283],"iteration":361,"passed_time":2.281205497,"remaining_time":4.020467147},
{"learn":[4.274426275],"iteration":362,"passed_time":2.28321143,"remaining_time":4.00662722},
{"learn":[4.273567658],"iteration":363,"passed_time":2.284739753,"remaining_time":3.992017811},
{"learn":[4.269488271],"iteration":364,"passed_time":2.286276214,"remaining_time":3.977494235},
{"learn":[4.266838205],"iteration":365,"passed_time":2.288077114,"remaining_time":3.963499701},
{"learn":[4.263456509],"iteration":366,"passed_time":2.289758418,"remaining_time":3.949365336},
{"learn":[4.260360204],"iteration":367,"passed_time":2.29221876,"remaining_time":3.936636566},
{"learn":[4.255120549],"iteration":368,"passed_time":2.2940831,"remaining_time":3.922944272},
{"learn":[4.252582211],"iteration":369,"passed_time":2.295939711,"remaining_time":3.909302751},
{"learn":[4.247857931],"iteration":370,"passed_time":2.297727433,"remaining_time":3.895607967},
{"learn":[4.245288911],"iteration":371,"passed_time":2.299520852,"remaining_time":3.881986815},
{"learn":[4.24048515],"iteration":372,"passed_time":2.303055317,"remaining_time":3.87135572},
{"learn":[4.2378365],"iteration":373,"passed_time":2.30512877,"remaining_time":3.85831714},
{"learn":[4.236751063],"iteration":374,"passed_time":2.307011658,"remaining_time":3.84501943},
{"learn":[4.233240093],"iteration":375,"passed_time":2.308856593,"remaining_time":3.831719453},
{"learn":[4.230358421],"iteration":376,"passed_time":2.31150215,"remaining_time":3.819803287},
{"learn":[4.225853583],"iteration":377,"passed_time":2.313545879,"remaining_time":3.806945864},
{"learn":[4.224702126],"iteration":378,"passed_time":2.31542445,"remaining_time":3.79387489},
{"learn":[4.224361982],"iteration":379,"passed_time":2.317168442,"remaining_time":3.780643247},
{"learn":[4.223787954],"iteration":380,"passed_time":2.31907177,"remaining_time":3.767730776},
{"learn":[4.22144054],"iteration":381,"passed_time":2.320889341,"remaining_time":3.754737206},
{"learn":[4.217739335],"iteration":382,"passed_time":2.322646144,"remaining_time":3.741704101},
{"learn":[4.215611665],"iteration":383,"passed_time":2.324347555,"remaining_time":3.728640869},
{"learn":[4.210236863],"iteration":384,"passed_time":2.326236108,"remaining_time":3.715935601},
{"learn":[4.208454294],"iteration":385,"passed_time":2.328356331,"remaining_time":3.703654889},
{"learn":[4.207446501],"iteration":386,"passed_time":2.331404109,"remaining_time":3.692895914},
{"learn":[4.204985442],"iteration":387,"passed_time":2.332921331,"remaining_time":3.679762511},
{"learn":[4.202796622],"iteration":388,"passed_time":2.334824305,"remaining_time":3.667294731},
{"learn":[4.199774004],"iteration":389,"passed_time":2.336639909,"remaining_time":3.654744473},
{"learn":[4.199458358],"iteration":390,"passed_time":2.338760691,"remaining_time":3.642724452},
{"learn":[4.19751254],"iteration":391,"passed_time":2.340590211,"remaining_time":3.630303185},
{"learn":[4.195201346],"iteration":392,"passed_time":2.342319524,"remaining_time":3.617781046},
{"learn":[4.190593508],"iteration":393,"passed_time":2.344222851,"remaining_time":3.60558134},
{"learn":[4.187212054],"iteration":394,"passed_time":2.346448549,"remaining_time":3.593927524},
{"learn":[4.184984466],"iteration":395,"passed_time":2.348335036,"remaining_time":3.581803944},
{"learn":[4.182832144],"iteration":396,"passed_time":2.350181755,"remaining_time":3.569671532},
{"learn":[4.179752812],"iteration":397,"passed_time":2.351712195,"remaining_time":3.557112415},
{"learn":[4.17878934],"iteration":398,"passed_time":2.3532068,"remaining_time":3.544554603},
{"learn":[4.174548229],"iteration":399,"passed_time":2.355495889,"remaining_time":3.533243833},
{"learn":[4.168872556],"iteration":400,"passed_time":2.358084057,"remaining_time":3.522424813},
{"learn":[4.163926494],"iteration":401,"passed_time":2.359846074,"remaining_time":3.510417792},
{"learn":[4.159485076],"iteration":402,"passed_time":2.361601041,"remaining_time":3.498451169},
{"learn":[4.155926102],"iteration":403,"passed_time":2.363318446,"remaining_time":3.486479687},
{"learn":[4.153540115],"iteration":404,"passed_time":2.365418793,"remaining_time":3.475121437},
{"learn":[4.150983044],"iteration":405,"passed_time":2.367219589,"remaining_time":3.463370532},
{"learn":[4.146539132],"iteration":406,"passed_time":2.368931112,"remaining_time":3.451538451},
{"learn":[4.144869174],"iteration":407,"passed_time":2.370671637,"remaining_time":3.439798062},
{"learn":[4.142825962],"iteration":408,"passed_time":2.372763307,"remaining_time":3.428613972},
{"learn":[4.142467378],"iteration":409,"passed_time":2.375297494,"remaining_time":3.418111028},
{"learn":[4.141800768],"iteration":410,"passed_time":2.376997941,"remaining_time":3.406452037},
{"learn":[4.140107084],"iteration":411,"passed_time":2.378481945,"remaining_time":3.394532484},
{"learn":[4.136243196],"iteration":412,"passed_time":2.380007352,"remaining_time":3.382722314},
{"learn":[4.133618439],"iteration":413,"passed_time":2.38129949,"remaining_time":3.370631646},
{"learn":[4.131053025],"iteration":414,"passed_time":2.38346792,"remaining_time":3.359828273},
{"learn":[4.128379975],"iteration":415,"passed_time":2.384741243,"remaining_time":3.347809822},
{"learn":[4.127068571],"iteration":416,"passed_time":2.386292789,"remaining_time":3.336231885},
{"learn":[4.125969877],"iteration":417,"passed_time":2.387557363,"remaining_time":3.324302357},
{"learn":[4.123893633],"iteration":418,"passed_time":2.388947441,"remaining_time":3.312597764},
{"learn":[4.119643722],"iteration":419,"passed_time":2.39040542,"remaining_time":3.301036056},
{"learn":[4.11465686],"iteration":420,"passed_time":2.392198099,"remaining_time":3.289982659},
{"learn":[4.111565986],"iteration":421,"passed_time":2.393503247,"remaining_time":3.278305395},
{"learn":[4.106322452],"iteration":422,"passed_time":2.394768331,"remaining_time":3.266622522},
{"learn":[4.104222175],"iteration":423,"passed_time":2.396026814,"remaining_time":3.254979823},
{"learn":[4.103008002],"iteration":424,"passed_time":2.397179817,"remaining_time":3.243243282},
{"learn":[4.099176337],"iteration":425,"passed_time":2.398446276,"remaining_time":3.231709301},
{"learn":[4.096525716],"iteration":426,"passed_time":2.400807733,"remaining_time":3.221692813},
{"learn":[4.094967724],"iteration":427,"passed_time":2.402836253,"remaining_time":3.211267141},
{"learn":[4.094683584],"iteration":428,"passed_time":2.404385581,"remaining_time":3.200242813},
{"learn":[4.091096563],"iteration":429,"passed_time":2.405670301,"remaining_time":3.188911794},
{"learn":[4.089178677],"iteration":430,"passed_time":2.406931454,"remaining_time":3.177596281},
{"learn":[4.085335077],"iteration":431,"passed_time":2.408273716,"remaining_time":3.16643396},
{"learn":[4.084852122],"iteration":432,"passed_time":2.410357645,"remaining_time":3.156288186},
{"learn":[4.080322952],"iteration":433,"passed_time":2.411619553,"remaining_time":3.145107528},
{"learn":[4.077449519],"iteration":434,"passed_time":2.412881048,"remaining_time":3.133971936},
{"learn":[4.076568374],"iteration":435,"passed_time":2.414176621,"remaining_time":3.12292572},
{"learn":[4.076071793],"iteration":436,"passed_time":2.415723829,"remaining_time":3.11224832},
{"learn":[4.075027644],"iteration":437,"passed_time":2.417202389,"remaining_time":3.101524527},
{"learn":[4.07020837],"iteration":438,"passed_time":2.419596695,"remaining_time":3.092013088},
{"learn":[4.06833694],"iteration":439,"passed_time":2.421029318,"remaining_time":3.081310041},
{"learn":[4.063936568],"iteration":440,"passed_time":2.422551462,"remaining_time":3.070762511},
{"learn":[4.061734926],"iteration":441,"passed_time":2.424006912,"remaining_time":3.060171622},
{"learn":[4.060815619],"iteration":442,"passed_time":2.425678471,"remaining_time":3.049893698},
{"learn":[4.056407489],"iteration":443,"passed_time":2.427820544,"remaining_time":3.040243744},
{"learn":[4.05238936],"iteration":444,"passed_time":2.429753885,"remaining_time":3.030367205},
{"learn":[4.049685254],"iteration":445,"passed_time":2.431395552,"remaining_time":3.020163981},
{"learn":[4.045162016],"iteration":446,"passed_time":2.432991743,"remaining_time":3.009942805},
{"learn":[4.042955482],"iteration":447,"passed_time":2.434676644,"remaining_time":2.999869436},
{"learn":[4.041467663],"iteration":448,"passed_time":2.437144254,"remaining_time":2.990793951},
{"learn":[4.038920476],"iteration":449,"passed_time":2.438946042,"remaining_time":2.980934051},
{"learn":[4.036694383],"iteration":450,"passed_time":2.440515473,"remaining_time":2.970827039},
{"learn":[4.034999007],"iteration":451,"passed_time":2.442099006,"remaining_time":2.960774901},
{"learn":[4.031928018],"iteration":452,"passed_time":2.443866125,"remaining_time":2.950981833},
{"learn":[4.028718143],"iteration":453,"passed_time":2.446025336,"remaining_time":2.941695669},
{"learn":[4.027401978],"iteration":454,"passed_time":2.447896504,"remaining_time":2.932095813},
{"learn":[4.025930598],"iteration":455,"passed_time":2.449398691,"remaining_time":2.922089666},
{"learn":[4.021074523],"iteration":456,"passed_time":2.450937617,"remaining_time":2.91216439},
{"learn":[4.020268486],"iteration":457,"passed_time":2.452367991,"remaining_time":2.902147273},
{"learn":[4.017986361],"iteration":458,"passed_time":2.454663988,"remaining_time":2.893187838},
{"learn":[4.014814804],"iteration":459,"passed_time":2.456455531,"remaining_time":2.883665188},
{"learn":[4.009704796],"iteration":460,"passed_time":2.458059307,"remaining_time":2.873956543},
{"learn":[4.008440457],"iteration":461,"passed_time":2.459458528,"remaining_time":2.864044779},
{"learn":[4.004854849],"iteration":462,"passed_time":2.461025831,"remaining_time":2.854364733},
{"learn":[4.000898028],"iteration":463,"passed_time":2.462897693,"remaining_time":2.845071473},
{"learn":[3.996617985],"iteration":464,"passed_time":2.465176457,"remaining_time":2.836278289},
{"learn":[3.995443319],"iteration":465,"passed_time":2.466765429,"remaining_time":2.826722616},
{"learn":[3.990771995],"iteration":466,"passed_time":2.468355012,"remaining_time":2.817201759},
{"learn":[3.989249359],"iteration":467,"passed_time":2.469913085,"remaining_time":2.807678977},
{"learn":[3.986599538],"iteration":468,"passed_time":2.473019111,"remaining_time":2.799942746},
{"learn":[3.985628919],"iteration":469,"passed_time":2.474831336,"remaining_time":2.790767251},
{"learn":[3.985086112],"iteration":470,"passed_time":2.476326833,"remaining_time":2.781267292},
{"learn":[3.98466839],"iteration":471,"passed_time":2.477752523,"remaining_time":2.771723161},
{"learn":[3.984233894],"iteration":472,"passed_time":2.479188079,"remaining_time":2.76222435},
{"learn":[3.981855845],"iteration":473,"passed_time":2.481544241,"remaining_time":2.753781161},
{"learn":[3.978684264],"iteration":474,"passed_time":2.483305163,"remaining_time":2.744705707},
{"learn":[3.974361269],"iteration":475,"passed_time":2.485247753,"remaining_time":2.735860972},
{"learn":[3.972074049],"iteration":476,"passed_time":2.486670963,"remaining_time":2.72647571},
{"learn":[3.97191982],"iteration":477,"passed_time":2.488057204,"remaining_time":2.717083391},
{"learn":[3.969616848],"iteration":478,"passed_time":2.489600016,"remaining_time":2.707894798},
{"learn":[3.968533527],"iteration":479,"passed_time":2.49157269,"remaining_time":2.699203747},
{"learn":[3.967568753],"iteration":480,"passed_time":2.493239391,"remaining_time":2.690210486},
{"learn":[3.966232553],"iteration":481,"passed_time":2.494702062,"remaining_time":2.681028357},
{"learn":[3.961522393],"iteration":482,"passed_time":2.496229545,"remaining_time":2.671947567},
{"learn":[3.955829553],"iteration":483,"passed_time":2.497709111,"remaining_time":2.662846904},
{"learn":[3.954248095],"iteration":484,"passed_time":2.502384909,"remaining_time":2.657171605},
{"learn":[3.951922606],"iteration":485,"passed_time":2.504517587,"remaining_time":2.648810781},
{"learn":[3.94978202],"iteration":486,"passed_time":2.506118271,"remaining_time":2.63991514},
{"learn":[3.949518999],"iteration":487,"passed_time":2.507689483,"remaining_time":2.631018474},
{"learn":[3.945431216],"iteration":488,"passed_time":2.510209435,"remaining_time":2.623143193},
{"learn":[3.943249086],"iteration":489,"passed_time":2.511859615,"remaining_time":2.614384498},
{"learn":[3.941981548],"iteration":490,"passed_time":2.514240972,"remaining_time":2.606412739},
{"learn":[3.936600517],"iteration":491,"passed_time":2.516585107,"remaining_time":2.598425273},
{"learn":[3.934476885],"iteration":492,"passed_time":2.519189039,"remaining_time":2.590727876},
{"learn":[3.93045798],"iteration":493,"passed_time":2.521152784,"remaining_time":2.582395362},
{"learn":[3.925977375],"iteration":494,"passed_time":2.522984063,"remaining_time":2.573953438},
{"learn":[3.92457993],"iteration":495,"passed_time":2.524850222,"remaining_time":2.565573612},
{"learn":[3.919849146],"iteration":496,"passed_time":2.527279296,"remaining_time":2.55778971},
{"learn":[3.919681964],"iteration":497,"passed_time":2.529117017,"remaining_time":2.54943121},
{"learn":[3.917633027],"iteration":498,"passed_time":2.530590152,"remaining_time":2.540732798},
{"learn":[3.916616419],"iteration":499,"passed_time":2.531960018,"remaining_time":2.531960018},
{"learn":[3.912896166],"iteration":500,"passed_time":2.533352478,"remaining_time":2.523239294},
{"learn":[3.912769674],"iteration":501,"passed_time":2.535043991,"remaining_time":2.514844437},
{"learn":[3.909373788],"iteration":502,"passed_time":2.537053042,"remaining_time":2.506789984},
{"learn":[3.906706036],"iteration":503,"passed_time":2.538562468,"remaining_time":2.498267826},
{"learn":[3.903895664],"iteration":504,"passed_time":2.539936037,"remaining_time":2.489640274},
{"learn":[3.902982967],"iteration":505,"passed_time":2.54278163,"remaining_time":2.482478509},
{"learn":[3.900905528],"iteration":506,"passed_time":2.546201394,"remaining_time":2.475892086},
{"learn":[3.897463465],"iteration":507,"passed_time":2.548597714,"remaining_time":2.468326919},
{"learn":[3.895918033],"iteration":508,"passed_time":2.55076087,"remaining_time":2.460557145},
{"learn":[3.893921936],"iteration":509,"passed_time":2.554211437,"remaining_time":2.454046283},
{"learn":[3.890237934],"iteration":510,"passed_time":2.556893011,"remaining_time":2.446811512},
{"learn":[3.887311613],"iteration":511,"passed_time":2.55897409,"remaining_time":2.43902218},
{"learn":[3.884869735],"iteration":512,"passed_time":2.560675322,"remaining_time":2.430894507},
{"learn":[3.882101231],"iteration":513,"passed_time":2.563398011,"remaining_time":2.423757653},
{"learn":[3.88060368],"iteration":514,"passed_time":2.56487456,"remaining_time":2.415464392},
{"learn":[3.877726076],"iteration":515,"passed_time":2.566170199,"remaining_time":2.407027861},
{"learn":[3.874938145],"iteration":516,"passed_time":2.567432868,"remaining_time":2.398588153},
{"learn":[3.874340833],"iteration":517,"passed_time":2.568663061,"remaining_time":2.390145937},
{"learn":[3.873105224],"iteration":518,"passed_time":2.570618543,"remaining_time":2.382403698},
{"learn":[3.869800236],"iteration":519,"passed_time":2.572734427,"remaining_time":2.374831778},
{"learn":[3.867932518],"iteration":520,"passed_time":2.574207139,"remaining_time":2.366689481},
{"learn":[3.866666962],"iteration":521,"passed_time":2.575714357,"remaining_time":2.358604335},
{"learn":[3.865527652],"iteration":522,"passed_time":2.577253021,"remaining_time":2.350573023},
{"learn":[3.861900081],"iteration":523,"passed_time":2.578790045,"remaining_time":2.342565003},
{"learn":[3.858502887],"iteration":524,"passed_time":2.581033112,"remaining_time":2.335220435},
{"learn":[3.858335097],"iteration":525,"passed_time":2.5827592,"remaining_time":2.327429393},
{"learn":[3.855719306],"iteration":526,"passed_time":2.585007699,"remaining_time":2.32013025},
{"learn":[3.855137428],"iteration":527,"passed_time":2.586630274,"remaining_time":2.3122907},
{"learn":[3.851985706],"iteration":528,"passed_time":2.588148247,"remaining_time":2.30438152},
{"learn":[3.851051809],"iteration":529,"passed_time":2.590542682,"remaining_time":2.297273699},
{"learn":[3.850679146],"iteration":530,"passed_time":2.592254592,"remaining_time":2.289580798},
{"learn":[3.848179484],"iteration":531,"passed_time":2.59380727,"remaining_time":2.281770305},
{"learn":[3.844551071],"iteration":532,"passed_time":2.59538862,"remaining_time":2.274008416},
{"learn":[3.841604794],"iteration":533,"passed_time":2.596844958,"remaining_time":2.266160581},
{"learn":[3.83969656],"iteration":534,"passed_time":2.599918122,"remaining_time":2.259741919},
{"learn":[3.836811463],"iteration":535,"passed_time":2.601566992,"remaining_time":2.252102769},
{"learn":[3.834182551],"iteration":536,"passed_time":2.603131603,"remaining_time":2.244413281},
{"learn":[3.828012842],"iteration":537,"passed_time":2.604566523,"remaining_time":2.236635193},
{"learn":[3.826636176],"iteration":538,"passed_time":2.606219247,"remaining_time":2.229066926},
{"learn":[3.826189798],"iteration":539,"passed_time":2.608502459,"remaining_time":2.22205765},
{"learn":[3.824104738],"iteration":540,"passed_time":2.610090817,"remaining_time":2.214476313},
{"learn":[3.82300218],"iteration":541,"passed_time":2.611566127,"remaining_time":2.206821561},
{"learn":[3.817146402],"iteration":542,"passed_time":2.61338916,"remaining_time":2.199482221},
{"learn":[3.814638044],"iteration":543,"passed_time":2.614806261,"remaining_time":2.191822895},
{"learn":[3.812979573],"iteration":544,"passed_time":2.616958597,"remaining_time":2.184800297},
{"learn":[3.811938825],"iteration":545,"passed_time":2.618228553,"remaining_time":2.177061837},
{"learn":[3.811479418],"iteration":546,"passed_time":2.619437527,"remaining_time":2.169296526},
{"learn":[3.80742981],"iteration":547,"passed_time":2.620642458,"remaining_time":2.161551808},
{"learn":[3.805097043],"iteration":548,"passed_time":2.62186557,"remaining_time":2.153845851},
{"learn":[3.801577232],"iteration":549,"passed_time":2.623074952,"remaining_time":2.146152234},
{"learn":[3.799762083],"iteration":550,"passed_time":2.624852825,"remaining_time":2.138945406},
{"learn":[3.796393455],"iteration":551,"passed_time":2.62692896,"remaining_time":2.132000315},
{"learn":[3.793486459],"iteration":552,"passed_time":2.628273705,"remaining_time":2.124481639},
{"learn":[3.792006091],"iteration":553,"passed_time":2.629583817,"remaining_time":2.116957369},
{"learn":[3.78932128],"iteration":554,"passed_time":2.630886173,"remaining_time":2.109449274},
{"learn":[3.787581812],"iteration":555,"passed_time":2.632207127,"remaining_time":2.101978354},
{"learn":[3.785308865],"iteration":556,"passed_time":2.634230897,"remaining_time":2.095088487},
{"learn":[3.78465475],"iteration":557,"passed_time":2.635851271,"remaining_time":2.087896526},
{"learn":[3.780498869],"iteration":558,"passed_time":2.637110038,"remaining_time":2.080439225},
{"learn":[3.778734909],"iteration":559,"passed_time":2.638303945,"remaining_time":2.0729531},
{"learn":[3.778652349],"iteration":560,"passed_time":2.639487024,"remaining_time":2.065480933},
{"learn":[3.777928006],"iteration":561,"passed_time":2.640905297,"remaining_time":2.058214449},
{"learn":[3.776131406],"iteration":562,"passed_time":2.642870249,"remaining_time":2.051393071},
{"learn":[3.772925617],"iteration":563,"passed_time":2.644398645,"remaining_time":2.044251435},
{"learn":[3.7727745],"iteration":564,"passed_time":2.645772786,"remaining_time":2.037010906},
{"learn":[3.771763073],"iteration":565,"passed_time":2.647011414,"remaining_time":2.029687197},
{"learn":[3.768738162],"iteration":566,"passed_time":2.648262572,"remaining_time":2.022394522},
{"learn":[3.767220794],"iteration":567,"passed_time":2.649787288,"remaining_time":2.015331177},
{"learn":[3.766691102],"iteration":568,"passed_time":2.651909029,"remaining_time":2.008739528},
{"learn":[3.766259335],"iteration":569,"passed_time":2.653247359,"remaining_time":2.001572569},
{"learn":[3.76116362],"iteration":570,"passed_time":2.655819556,"remaining_time":1.995353047},
{"learn":[3.758633056],"iteration":571,"passed_time":2.657202927,"remaining_time":1.988256735},
{"learn":[3.754603809],"iteration":572,"passed_time":2.658554138,"remaining_time":1.981156399},
{"learn":[3.754070549],"iteration":573,"passed_time":2.659904877,"remaining_time":1.974075745},
{"learn":[3.750534319],"iteration":574,"passed_time":2.661906798,"remaining_time":1.967496329},
{"learn":[3.746491516],"iteration":575,"passed_time":2.663173023,"remaining_time":1.960391253},
{"learn":[3.744210544],"iteration":576,"passed_time":2.664448479,"remaining_time":1.953313183},
{"learn":[3.742929991],"iteration":577,"passed_time":2.66568298,"remaining_time":1.94622529},
{"learn":[3.740402992],"iteration":578,"passed_time":2.667047453,"remaining_time":1.93925212},
{"learn":[3.739644243],"iteration":579,"passed_time":2.668300834,"remaining_time":1.932217845},
{"learn":[3.737529404],"iteration":580,"passed_time":2.670416923,"remaining_time":1.925825629},
{"learn":[3.737196923],"iteration":581,"passed_time":2.671748505,"remaining_time":1.918884665},
{"learn":[3.733954464],"iteration":582,"passed_time":2.673806516,"remaining_time":1.912482534},
{"learn":[3.731608623],"iteration":583,"passed_time":2.675732476,"remaining_time":1.906001215},
{"learn":[3.729843952],"iteration":584,"passed_time":2.677329965,"remaining_time":1.899302453},
{"learn":[3.727223798],"iteration":585,"passed_time":2.679340936,"remaining_time":1.892913221},
{"learn":[3.725351667],"iteration":586,"passed_time":2.681178535,"remaining_time":1.886416925},
{"learn":[3.725026912],"iteration":587,"passed_time":2.682541952,"remaining_time":1.879604225},
{"learn":[3.721974565],"iteration":588,"passed_time":2.683834909,"remaining_time":1.872760862},
{"learn":[3.720269493],"iteration":589,"passed_time":2.685148727,"remaining_time":1.86595081},
{"learn":[3.718907466],"iteration":590,"passed_time":2.686476076,"remaining_time":1.859168723},
{"learn":[3.715602912],"iteration":591,"passed_time":2.688560136,"remaining_time":1.85292658},
{"learn":[3.714463059],"iteration":592,"passed_time":2.689814997,"remaining_time":1.846129349},
{"learn":[3.710802077],"iteration":593,"passed_time":2.691129565,"remaining_time":1.839391588},
{"learn":[3.708032435],"iteration":594,"passed_time":2.692376989,"remaining_time":1.832626354},
{"learn":[3.703788939],"iteration":595,"passed_time":2.693648074,"remaining_time":1.825895674},
{"learn":[3.702500944],"iteration":596,"passed_time":2.69549595,"remaining_time":1.819572643},
{"learn":[3.698196925],"iteration":597,"passed_time":2.697315082,"remaining_time":1.813245256},
{"learn":[3.69658891],"iteration":598,"passed_time":2.698562998,"remaining_time":1.806550521},
{"learn":[3.696124066],"iteration":599,"passed_time":2.699782708,"remaining_time":1.799855138},
{"learn":[3.693537052],"iteration":600,"passed_time":2.701068307,"remaining_time":1.793221721},
{"learn":[3.691343275],"iteration":601,"passed_time":2.702278196,"remaining_time":1.786556017},
{"learn":[3.690973831],"iteration":602,"passed_time":2.703576972,"remaining_time":1.779966929},
{"learn":[3.686151073],"iteration":603,"passed_time":2.705589446,"remaining_time":1.773863279},
{"learn":[3.683921982],"iteration":604,"passed_time":2.70710264,"remaining_time":1.767447178},
{"learn":[3.679975271],"iteration":605,"passed_time":2.708442626,"remaining_time":1.760934644},
{"learn":[3.674047638],"iteration":606,"passed_time":2.710329679,"remaining_time":1.754793351},
{"learn":[3.673151794],"iteration":607,"passed_time":2.711657273,"remaining_time":1.748305347},
{"learn":[3.670953108],"iteration":608,"passed_time":2.712951409,"remaining_time":1.741812809},
{"learn":[3.6703947],"iteration":609,"passed_time":2.715091796,"remaining_time":1.735878361},
{"learn":[3.668433805],"iteration":610,"passed_time":2.716384676,"remaining_time":1.729416758},
{"learn":[3.668304956],"iteration":611,"passed_time":2.717623519,"remaining_time":1.722937786},
{"learn":[3.667880012],"iteration":612,"passed_time":2.718868231,"remaining_time":1.716479617},
{"learn":[3.667282264],"iteration":613,"passed_time":2.720093784,"remaining_time":1.710026385},
{"learn":[3.664611483],"iteration":614,"passed_time":2.721428701,"remaining_time":1.703658618},
{"learn":[3.662543394],"iteration":615,"passed_time":2.72355446,"remaining_time":1.697800183},
{"learn":[3.659041959],"iteration":616,"passed_time":2.725617091,"remaining_time":1.691914661},
{"learn":[3.656868545],"iteration":617,"passed_time":2.72711621,"remaining_time":1.685693191},
{"learn":[3.654785614],"iteration":618,"passed_time":2.728635498,"remaining_time":1.679499394},
{"learn":[3.654566096],"iteration":619,"passed_time":2.729883698,"remaining_time":1.673154524},
{"learn":[3.651007045],"iteration":620,"passed_time":2.731399983,"remaining_time":1.666989683},
{"learn":[3.648921786],"iteration":621,"passed_time":2.733304149,"remaining_time":1.661075512},
{"learn":[3.647655706],"iteration":622,"passed_time":2.734572022,"remaining_time":1.654789169},
{"learn":[3.647241144],"iteration":623,"passed_time":2.735819709,"remaining_time":1.648506748},
{"learn":[3.644195689],"iteration":624,"passed_time":2.737017485,"remaining_time":1.642210491},
{"learn":[3.642632246],"iteration":625,"passed_time":2.739026435,"remaining_time":1.636415155},
{"learn":[3.642523322],"iteration":626,"passed_time":2.740736368,"remaining_time":1.630454011},
{"learn":[3.641494659],"iteration":627,"passed_time":2.743189526,"remaining_time":1.624946662},
{"learn":[3.63976496],"iteration":628,"passed_time":2.744798916,"remaining_time":1.618951348},
{"learn":[3.637945652],"iteration":629,"passed_time":2.746718703,"remaining_time":1.613152254},
{"learn":[3.636233667],"iteration":630,"passed_time":2.748517598,"remaining_time":1.60729476},
{"learn":[3.635304404],"iteration":631,"passed_time":2.751550164,"remaining_time":1.60216845},
{"learn":[3.632234951],"iteration":632,"passed_time":2.753933249,"remaining_time":1.5966722},
{"learn":[3.631630987],"iteration":633,"passed_time":2.755263604,"remaining_time":1.590578043},
{"learn":[3.630301009],"iteration":634,"passed_time":2.756726266,"remaining_time":1.584574941},
{"learn":[3.629077964],"iteration":635,"passed_time":2.758061402,"remaining_time":1.57851313},
{"learn":[3.628004522],"iteration":636,"passed_time":2.760268955,"remaining_time":1.572963313},
{"learn":[3.625062876],"iteration":637,"passed_time":2.761565748,"remaining_time":1.566907211},
{"learn":[3.624917986],"iteration":638,"passed_time":2.762816758,"remaining_time":1.56084014},
{"learn":[3.622887087],"iteration":639,"passed_time":2.76410963,"remaining_time":1.554811667},
{"learn":[3.621220865],"iteration":640,"passed_time":2.765348032,"remaining_time":1.548767463},
{"learn":[3.621143844],"iteration":641,"passed_time":2.767403203,"remaining_time":1.543193686},
{"learn":[3.620822821],"iteration":642,"passed_time":2.769121146,"remaining_time":1.537443622},
{"learn":[3.619202826],"iteration":643,"passed_time":2.770416872,"remaining_time":1.531472681},
{"learn":[3.618204882],"iteration":644,"passed_time":2.771660552,"remaining_time":1.52548759},
{"learn":[3.614259666],"iteration":645,"passed_time":2.772920456,"remaining_time":1.519526071},
{"learn":[3.613415661],"iteration":646,"passed_time":2.774173794,"remaining_time":1.513575501},
{"learn":[3.611096773],"iteration":647,"passed_time":2.77553766,"remaining_time":1.50769947},
{"learn":[3.610820695],"iteration":648,"passed_time":2.777665036,"remaining_time":1.502250274},
{"learn":[3.609290065],"iteration":649,"passed_time":2.779125758,"remaining_time":1.496452331},
{"learn":[3.60897947],"iteration":650,"passed_time":2.780505656,"remaining_time":1.490624384},
{"learn":[3.606570702],"iteration":651,"passed_time":2.781827379,"remaining_time":1.484779031},
{"learn":[3.606292637],"iteration":652,"passed_time":2.783077211,"remaining_time":1.47890933},
{"learn":[3.602753838],"iteration":653,"passed_time":2.784316493,"remaining_time":1.473048175},
{"learn":[3.599755869],"iteration":654,"passed_time":2.786231495,"remaining_time":1.467557047},
{"learn":[3.599509575],"iteration":655,"passed_time":2.787882801,"remaining_time":1.461938542},
{"learn":[3.595337722],"iteration":656,"passed_time":2.789199655,"remaining_time":1.456157506},
{"learn":[3.595168561],"iteration":657,"passed_time":2.790439463,"remaining_time":1.450349995},
{"learn":[3.59290559],"iteration":658,"passed_time":2.791675888,"remaining_time":1.444554595},
{"learn":[3.592015928],"iteration":659,"passed_time":2.793133903,"remaining_time":1.438887162},
{"learn":[3.590680403],"iteration":660,"passed_time":2.795701467,"remaining_time":1.433801509},
{"learn":[3.590361532],"iteration":661,"passed_time":2.797141684,"remaining_time":1.428147869},
{"learn":[3.589069739],"iteration":662,"passed_time":2.798377451,"remaining_time":1.422403018},
{"learn":[3.585010186],"iteration":663,"passed_time":2.799631914,"remaining_time":1.416681209},
{"learn":[3.582997552],"iteration":664,"passed_time":2.800943171,"remaining_time":1.411001447},
{"learn":[3.582119256],"iteration":665,"passed_time":2.802301325,"remaining_time":1.405358322},
{"learn":[3.579019356],"iteration":666,"passed_time":2.804100411,"remaining_time":1.399948181},
{"learn":[3.57719559],"iteration":667,"passed_time":2.805579155,"remaining_time":1.39438964},
{"learn":[3.574050046],"iteration":668,"passed_time":2.806890429,"remaining_time":1.388760437},
{"learn":[3.572204518],"iteration":669,"passed_time":2.80846431,"remaining_time":1.383273466},
{"learn":[3.569508025],"iteration":670,"passed_time":2.809860815,"remaining_time":1.377711189},
{"learn":[3.566268704],"iteration":671,"passed_time":2.811528415,"remaining_time":1.372293631},
{"learn":[3.562564052],"iteration":672,"passed_time":2.81372746,"remaining_time":1.367145437},
{"learn":[3.561173586],"iteration":673,"passed_time":2.815029726,"remaining_time":1.361572241},
{"learn":[3.559551904],"iteration":674,"passed_time":2.816319134,"remaining_time":1.356005509},
{"learn":[3.558593054],"iteration":675,"passed_time":2.8175855,"remaining_time":1.350440388},
{"learn":[3.555647008],"iteration":676,"passed_time":2.81884857,"remaining_time":1.344886393},
{"learn":[3.553100059],"iteration":677,"passed_time":2.820095802,"remaining_time":1.339337534},
{"learn":[3.55085578],"iteration":678,"passed_time":2.82201487,"remaining_time":1.334118959},
{"learn":[3.550737965],"iteration":679,"passed_time":2.823821898,"remaining_time":1.328857364},
{"learn":[3.549408772],"iteration":680,"passed_time":2.825125862,"remaining_time":1.323370264},
{"learn":[3.547390589],"iteration":681,"passed_time":2.826334999,"remaining_time":1.317851216},
{"learn":[3.54723575],"iteration":682,"passed_time":2.827532372,"remaining_time":1.312339329},
{"learn":[3.543988891],"iteration":683,"passed_time":2.828829885,"remaining_time":1.306886321},
{"learn":[3.543868508],"iteration":684,"passed_time":2.830240635,"remaining_time":1.301497518},
{"learn":[3.542752124],"iteration":685,"passed_time":2.832147476,"remaining_time":1.296347387},
{"learn":[3.541334315],"iteration":686,"passed_time":2.833504743,"remaining_time":1.290956309},
{"learn":[3.540208266],"iteration":687,"passed_time":2.8347641,"remaining_time":1.285532557},
{"learn":[3.537730983],"iteration":688,"passed_time":2.836159494,"remaining_time":1.280182297},
{"learn":[3.53419867],"iteration":689,"passed_time":2.838204677,"remaining_time":1.275135435},
{"learn":[3.532628335],"iteration":690,"passed_time":2.84027803,"remaining_time":1.270109857},
{"learn":[3.532204987],"iteration":691,"passed_time":2.841615612,"remaining_time":1.26476533},
{"learn":[3.530618147],"iteration":692,"passed_time":2.842955784,"remaining_time":1.259433514},
{"learn":[3.528909306],"iteration":693,"passed_time":2.844155336,"remaining_time":1.2540512},
{"learn":[3.526700678],"iteration":694,"passed_time":2.845437275,"remaining_time":1.248717078},
{"learn":[3.526439574],"iteration":695,"passed_time":2.846639827,"remaining_time":1.243359925},
{"learn":[3.525784216],"iteration":696,"passed_time":2.847876854,"remaining_time":1.23802968},
{"learn":[3.524112693],"iteration":697,"passed_time":2.849756863,"remaining_time":1.232989359},
{"learn":[3.522813541],"iteration":698,"passed_time":2.851348937,"remaining_time":1.227834092},
{"learn":[3.519148203],"iteration":699,"passed_time":2.852729467,"remaining_time":1.222598343},
{"learn":[3.517236747],"iteration":700,"passed_time":2.854070063,"remaining_time":1.21735656},
{"learn":[3.515603888],"iteration":701,"passed_time":2.855345944,"remaining_time":1.212098421},
{"learn":[3.51263524],"iteration":702,"passed_time":2.856629832,"remaining_time":1.206854993},
{"learn":[3.51123442],"iteration":703,"passed_time":2.858626207,"remaining_time":1.201922383},
{"learn":[3.50828027],"iteration":704,"passed_time":2.860034026,"remaining_time":1.196751826},
{"learn":[3.508265537],"iteration":705,"passed_time":2.860815686,"remaining_time":1.191331178},
{"learn":[3.506774876],"iteration":706,"passed_time":2.862055057,"remaining_time":1.18611334},
{"learn":[3.50552068],"iteration":707,"passed_time":2.863261861,"remaining_time":1.18089331},
{"learn":[3.501973993],"iteration":708,"passed_time":2.864490835,"remaining_time":1.1756937},
{"learn":[3.498880354],"iteration":709,"passed_time":2.867661646,"remaining_time":1.171298419},
{"learn":[3.497370959],"iteration":710,"passed_time":2.869329542,"remaining_time":1.166295693},
{"learn":[3.496050455],"iteration":711,"passed_time":2.870693451,"remaining_time":1.161179373},
{"learn":[3.495630067],"iteration":712,"passed_time":2.871931187,"remaining_time":1.156022792},
{"learn":[3.49550669],"iteration":713,"passed_time":2.873198666,"remaining_time":1.150889101},
{"learn":[3.493652375],"iteration":714,"passed_time":2.874672258,"remaining_time":1.145848382},
{"learn":[3.491915684],"iteration":715,"passed_time":2.876676949,"remaining_time":1.141028287},
{"learn":[3.490303956],"iteration":716,"passed_time":2.877963714,"remaining_time":1.135932679},
{"learn":[3.488363853],"iteration":717,"passed_time":2.879530022,"remaining_time":1.130957474},
{"learn":[3.485483936],"iteration":718,"passed_time":2.880795443,"remaining_time":1.125874158},
{"learn":[3.483763466],"iteration":719,"passed_time":2.882092122,"remaining_time":1.120813603},
{"learn":[3.481642352],"iteration":720,"passed_time":2.883641741,"remaining_time":1.115861367},
{"learn":[3.479826119],"iteration":721,"passed_time":2.885526367,"remaining_time":1.111047548},
{"learn":[3.478588728],"iteration":722,"passed_time":2.886833289,"remaining_time":1.106020499},
{"learn":[3.475390887],"iteration":723,"passed_time":2.888074141,"remaining_time":1.10097854},
{"learn":[3.472636852],"iteration":724,"passed_time":2.889354975,"remaining_time":1.095962232},
{"learn":[3.47061883],"iteration":725,"passed_time":2.890725162,"remaining_time":1.090989937},
{"learn":[3.46953149],"iteration":726,"passed_time":2.891929127,"remaining_time":1.085965133},
{"learn":[3.467217162],"iteration":727,"passed_time":2.894106102,"remaining_time":1.081314368},
{"learn":[3.465686216],"iteration":728,"passed_time":2.895476842,"remaining_time":1.076370678},
{"learn":[3.462631216],"iteration":729,"passed_time":2.896781583,"remaining_time":1.071412366},
{"learn":[3.461451053],"iteration":730,"passed_time":2.898042073,"remaining_time":1.066447767},
{"learn":[3.458950469],"iteration":731,"passed_time":2.89939824,"remaining_time":1.061528317},
{"learn":[3.458072145],"iteration":732,"passed_time":2.900780858,"remaining_time":1.056628225},
{"learn":[3.454364268],"iteration":733,"passed_time":2.902655041,"remaining_time":1.05191586},
{"learn":[3.453243406],"iteration":734,"passed_time":2.903976996,"remaining_time":1.047012114},
{"learn":[3.453017963],"iteration":735,"passed_time":2.905229664,"remaining_time":1.042093249},
{"learn":[3.45201581],"iteration":736,"passed_time":2.90647771,"remaining_time":1.037182684},
{"learn":[3.449510107],"iteration":737,"passed_time":2.909074813,"remaining_time":1.032760977},
{"learn":[3.447189189],"iteration":738,"passed_time":2.911649151,"remaining_time":1.028336169},
{"learn":[3.446423605],"iteration":739,"passed_time":2.913724399,"remaining_time":1.023741005},
{"learn":[3.445531987],"iteration":740,"passed_time":2.91534479,"remaining_time":1.018993658},
{"learn":[3.445328199],"iteration":741,"passed_time":2.916792739,"remaining_time":1.01419478},
{"learn":[3.443327544],"iteration":742,"passed_time":2.918566983,"remaining_time":1.009517786},
{"learn":[3.441475798],"iteration":743,"passed_time":2.921355473,"remaining_time":1.005197582},
{"learn":[3.439046501],"iteration":744,"passed_time":2.923527384,"remaining_time":1.000670447},
{"learn":[3.435899469],"iteration":745,"passed_time":2.924855223,"remaining_time":0.9958622341},
{"learn":[3.433988352],"iteration":746,"passed_time":2.926119131,"remaining_time":0.9910416868},
{"learn":[3.433413263],"iteration":747,"passed_time":2.92740635,"remaining_time":0.9862385029},
{"learn":[3.429944699],"iteration":748,"passed_time":2.929273557,"remaining_time":0.9816390692},
{"learn":[3.429291634],"iteration":749,"passed_time":2.930781368,"remaining_time":0.9769271227},
{"learn":[3.429175603],"iteration":750,"passed_time":2.932014454,"remaining_time":0.9721326219},
{"learn":[3.428780323],"iteration":751,"passed_time":2.933252178,"remaining_time":0.9673491225},
{"learn":[3.423893341],"iteration":752,"passed_time":2.93449889,"remaining_time":0.9625779892},
{"learn":[3.421024316],"iteration":753,"passed_time":2.935794789,"remaining_time":0.957832252},
{"learn":[3.420969872],"iteration":754,"passed_time":2.937558577,"remaining_time":0.9532474853},
{"learn":[3.419544785],"iteration":755,"passed_time":2.939554385,"remaining_time":0.9487450659},
{"learn":[3.417057977],"iteration":756,"passed_time":2.940976299,"remaining_time":0.9440650472},
{"learn":[3.415160245],"iteration":757,"passed_time":2.942255586,"remaining_time":0.9393480895},
{"learn":[3.412854597],"iteration":758,"passed_time":2.943502236,"remaining_time":0.9346298272},
{"learn":[3.410926347],"iteration":759,"passed_time":2.944832269,"remaining_time":0.9299470323},
{"learn":[3.408963843],"iteration":760,"passed_time":2.946618276,"remaining_time":0.9254162524},
{"learn":[3.407629634],"iteration":761,"passed_time":2.948122487,"remaining_time":0.9208046612},
{"learn":[3.404384724],"iteration":762,"passed_time":2.949449094,"remaining_time":0.9161460487},
{"learn":[3.403041656],"iteration":763,"passed_time":2.951059451,"remaining_time":0.9115838094},
{"learn":[3.401101731],"iteration":764,"passed_time":2.95234544,"remaining_time":0.906929645},
{"learn":[3.400890668],"iteration":765,"passed_time":2.953595448,"remaining_time":0.9022732832},
{"learn":[3.399289941],"iteration":766,"passed_time":2.955483695,"remaining_time":0.8978196883},
{"learn":[3.399202366],"iteration":767,"passed_time":2.957203787,"remaining_time":0.8933219773},
{"learn":[3.397447845],"iteration":768,"passed_time":2.958508055,"remaining_time":0.8887065807},
{"learn":[3.394655341],"iteration":769,"passed_time":2.959769764,"remaining_time":0.8840870724},
{"learn":[3.393228229],"iteration":770,"passed_time":2.961048244,"remaining_time":0.8794812555},
{"learn":[3.389691197],"iteration":771,"passed_time":2.962333009,"remaining_time":0.8748859146},
{"learn":[3.389626772],"iteration":772,"passed_time":2.963777731,"remaining_time":0.8703461125},
{"learn":[3.388480222],"iteration":773,"passed_time":2.966359757,"remaining_time":0.8661463889},
{"learn":[3.388215066],"iteration":774,"passed_time":2.967717051,"remaining_time":0.861595273},
{"learn":[3.386324358],"iteration":775,"passed_time":2.968999078,"remaining_time":0.8570306618},
{"learn":[3.383913061],"iteration":776,"passed_time":2.970228596,"remaining_time":0.8524594298},
{"learn":[3.382839768],"iteration":777,"passed_time":2.971504389,"remaining_time":0.8479099926},
{"learn":[3.381961844],"iteration":778,"passed_time":2.97363083,"remaining_time":0.8436102869},
{"learn":[3.381521703],"iteration":779,"passed_time":2.975119712,"remaining_time":0.839136329},
{"learn":[3.380918963],"iteration":780,"passed_time":2.976424387,"remaining_time":0.8346183619},
{"learn":[3.377139006],"iteration":781,"passed_time":2.97768498,"remaining_time":0.8300963245},
{"learn":[3.376004372],"iteration":782,"passed_time":2.979644316,"remaining_time":0.8257762663},
{"learn":[3.373826468],"iteration":783,"passed_time":2.980976836,"remaining_time":0.8212895364},
{"learn":[3.373546786],"iteration":784,"passed_time":2.983037232,"remaining_time":0.8170101973},
{"learn":[3.372109181],"iteration":785,"passed_time":2.984386771,"remaining_time":0.812542963},
{"learn":[3.370764924],"iteration":786,"passed_time":2.985635437,"remaining_time":0.8080563508},
{"learn":[3.367833107],"iteration":787,"passed_time":2.98690408,"remaining_time":0.8035833311},
{"learn":[3.36450404],"iteration":788,"passed_time":2.98812691,"remaining_time":0.7991061826},
{"learn":[3.361794558],"iteration":789,"passed_time":2.989419454,"remaining_time":0.7946558041},
{"learn":[3.356880529],"iteration":790,"passed_time":2.991051296,"remaining_time":0.7903030605},
{"learn":[3.353843509],"iteration":791,"passed_time":2.993065105,"remaining_time":0.7860575022},
{"learn":[3.353640253],"iteration":792,"passed_time":2.994356512,"remaining_time":0.7816290012},
{"learn":[3.353055088],"iteration":793,"passed_time":2.995588993,"remaining_time":0.777193114},
{"learn":[3.351415617],"iteration":794,"passed_time":2.996827169,"remaining_time":0.7727667542},
{"learn":[3.349169061],"iteration":795,"passed_time":2.998022554,"remaining_time":0.7683374385},
{"learn":[3.346211014],"iteration":796,"passed_time":2.999341754,"remaining_time":0.7639477743},
{"learn":[3.344560452],"iteration":797,"passed_time":3.001054825,"remaining_time":0.7596655072},
{"learn":[3.344445461],"iteration":798,"passed_time":3.002327736,"remaining_time":0.7552789423},
{"learn":[3.342608898],"iteration":799,"passed_time":3.003574591,"remaining_time":0.7508936477},
{"learn":[3.339572899],"iteration":800,"passed_time":3.004826961,"remaining_time":0.7465175595},
{"learn":[3.339309302],"iteration":801,"passed_time":3.006045139,"remaining_time":0.7421408197},
{"learn":[3.33698088],"iteration":802,"passed_time":3.007985257,"remaining_time":0.7379490607},
{"learn":[3.334746342],"iteration":803,"passed_time":3.009471483,"remaining_time":0.7336522522},
{"learn":[3.332048511],"iteration":804,"passed_time":3.010787092,"remaining_time":0.7293210968},
{"learn":[3.331932544],"iteration":805,"passed_time":3.012021129,"remaining_time":0.7249777903},
{"learn":[3.330541133],"iteration":806,"passed_time":3.013248721,"remaining_time":0.7206406482},
{"learn":[3.329124989],"iteration":807,"passed_time":3.014508754,"remaining_time":0.7163189119},
{"learn":[3.32583918],"iteration":808,"passed_time":3.01637501,"remaining_time":0.71214787},
{"learn":[3.325287299],"iteration":809,"passed_time":3.017902954,"remaining_time":0.707903162},
{"learn":[3.322745162],"iteration":810,"passed_time":3.019720443,"remaining_time":0.7037326309},
{"learn":[3.319733662],"iteration":811,"passed_time":3.020962438,"remaining_time":0.6994346532},
{"learn":[3.318080007],"iteration":812,"passed_time":3.022229894,"remaining_time":0.6951500495},
{"learn":[3.317179538],"iteration":813,"passed_time":3.023776161,"remaining_time":0.6909365676},
{"learn":[3.315685949],"iteration":814,"passed_time":3.026199851,"remaining_time":0.6869288006},
{"learn":[3.314944576],"iteration":815,"passed_time":3.027941781,"remaining_time":0.6827711859},
{"learn":[3.312369052],"iteration":816,"passed_time":3.029334528,"remaining_time":0.6785412712},
{"learn":[3.312321621],"iteration":817,"passed_time":3.03030464,"remaining_time":0.6742242597},
{"learn":[3.309465776],"iteration":818,"passed_time":3.031611878,"remaining_time":0.6699899266},
{"learn":[3.308307377],"iteration":819,"passed_time":3.03538522,"remaining_time":0.6663040728},
{"learn":[3.308076804],"iteration":820,"passed_time":3.03769171,"remaining_time":0.6622981925},
{"learn":[3.305643326],"iteration":821,"passed_time":3.039230655,"remaining_time":0.6581302392},
{"learn":[3.304154814],"iteration":822,"passed_time":3.040661559,"remaining_time":0.6539454386},
{"learn":[3.303076321],"iteration":823,"passed_time":3.042088709,"remaining_time":0.6497665204},
{"learn":[3.301746372],"iteration":824,"passed_time":3.044864096,"remaining_time":0.6458802627},
{"learn":[3.301345455],"iteration":825,"passed_time":3.046423184,"remaining_time":0.6417404769},
{"learn":[3.299181039],"iteration":826,"passed_time":3.048251137,"remaining_time":0.6376631762},
{"learn":[3.297989357],"iteration":827,"passed_time":3.049627335,"remaining_time":0.6334974657},
{"learn":[3.294775182],"iteration":828,"passed_time":3.05107323,"remaining_time":0.6293528618},
{"learn":[3.293840636],"iteration":829,"passed_time":3.053325965,"remaining_time":0.6253800169},
{"learn":[3.289279397],"iteration":830,"passed_time":3.055005279,"remaining_time":0.6212946958},
{"learn":[3.286204979],"iteration":831,"passed_time":3.056357725,"remaining_time":0.6171491559},
{"learn":[3.284833593],"iteration":832,"passed_time":3.057699371,"remaining_time":0.6130081571},
{"learn":[3.283519914],"iteration":833,"passed_time":3.059048335,"remaining_time":0.608875328},
{"learn":[3.282853026],"iteration":834,"passed_time":3.061242233,"remaining_time":0.6049161299},
{"learn":[3.281944673],"iteration":835,"passed_time":3.063549386,"remaining_time":0.6009833725},
{"learn":[3.279764865],"iteration":836,"passed_time":3.065352396,"remaining_time":0.5969563208},
{"learn":[3.277468839],"iteration":837,"passed_time":3.066836515,"remaining_time":0.5928729301},
{"learn":[3.277124974],"iteration":838,"passed_time":3.068227232,"remaining_time":0.5887778121},
{"learn":[3.275636037],"iteration":839,"passed_time":3.070579184,"remaining_time":0.5848722256},
{"learn":[3.274413635],"iteration":840,"passed_time":3.072632532,"remaining_time":0.5809138793},
{"learn":[3.272636087],"iteration":841,"passed_time":3.074009992,"remaining_time":0.5768332289},
{"learn":[3.269644466],"iteration":842,"passed_time":3.075942252,"remaining_time":0.5728623174},
{"learn":[3.26852083],"iteration":843,"passed_time":3.078067339,"remaining_time":0.5689318778},
{"learn":[3.267820927],"iteration":844,"passed_time":3.080876148,"remaining_time":0.5651311277},
{"learn":[3.267331099],"iteration":845,"passed_time":3.082417788,"remaining_time":0.5611020559},
{"learn":[3.267231014],"iteration":846,"passed_time":3.083744176,"remaining_time":0.5570399751},
{"learn":[3.267158695],"iteration":847,"passed_time":3.08496742,"remaining_time":0.5529658584},
{"learn":[3.264718705],"iteration":848,"passed_time":3.08634695,"remaining_time":0.5489262537},
{"learn":[3.261678512],"iteration":849,"passed_time":3.088091671,"remaining_time":0.5449573537},
{"learn":[3.261368381],"iteration":850,"passed_time":3.090992117,"remaining_time":0.5411960346},
{"learn":[3.260128799],"iteration":851,"passed_time":3.092610753,"remaining_time":0.5372140745},
{"learn":[3.258972952],"iteration":852,"passed_time":3.093974438,"remaining_time":0.5331937191},
{"learn":[3.258724846],"iteration":853,"passed_time":3.095285994,"remaining_time":0.5291706734},
{"learn":[3.25686724],"iteration":854,"passed_time":3.09744847,"remaining_time":0.5252982785},
{"learn":[3.255750259],"iteration":855,"passed_time":3.099542123,"remaining_time":0.5214183011},
{"learn":[3.254915866],"iteration":856,"passed_time":3.101061843,"remaining_time":0.5174467252},
{"learn":[3.254348625],"iteration":857,"passed_time":3.102674751,"remaining_time":0.5134962874},
{"learn":[3.253408514],"iteration":858,"passed_time":3.106586196,"remaining_time":0.509928584},
{"learn":[3.253291714],"iteration":859,"passed_time":3.108568443,"remaining_time":0.5060460256},
{"learn":[3.250186342],"iteration":860,"passed_time":3.10997693,"remaining_time":0.5020752536},
{"learn":[3.249141318],"iteration":861,"passed_time":3.111410396,"remaining_time":0.4981144254},
{"learn":[3.246300388],"iteration":862,"passed_time":3.112763984,"remaining_time":0.4941467739},
{"learn":[3.245205135],"iteration":863,"passed_time":3.114198275,"remaining_time":0.4901978766},
{"learn":[3.244403535],"iteration":864,"passed_time":3.116896633,"remaining_time":0.4864520757},
{"learn":[3.244211781],"iteration":865,"passed_time":3.119342287,"remaining_time":0.4826695917},
{"learn":[3.242286347],"iteration":866,"passed_time":3.120755093,"remaining_time":0.4787317502},
{"learn":[3.239606746],"iteration":867,"passed_time":3.122126477,"remaining_time":0.4747934274},
{"learn":[3.236773361],"iteration":868,"passed_time":3.123501854,"remaining_time":0.4708616143},
{"learn":[3.234552446],"iteration":869,"passed_time":3.125842746,"remaining_time":0.4670799506},
{"learn":[3.233724647],"iteration":870,"passed_time":3.127948421,"remaining_time":0.463266758},
{"learn":[3.230851485],"iteration":871,"passed_time":3.129368945,"remaining_time":0.4593569094},
{"learn":[3.227728941],"iteration":872,"passed_time":3.130784107,"remaining_time":0.4554519836},
{"learn":[3.225787575],"iteration":873,"passed_time":3.132474284,"remaining_time":0.4515924025},
{"learn":[3.222797487],"iteration":874,"passed_time":3.135607703,"remaining_time":0.4479439576},
{"learn":[3.22137014],"iteration":875,"passed_time":3.137403917,"remaining_time":0.4441074038},
{"learn":[3.219701963],"iteration":876,"passed_time":3.138777139,"remaining_time":0.4402161779},
{"learn":[3.21783327],"iteration":877,"passed_time":3.140189045,"remaining_time":0.4363360632},
{"learn":[3.217713355],"iteration":878,"passed_time":3.141577644,"remaining_time":0.432458356},
{"learn":[3.217666091],"iteration":879,"passed_time":3.144552317,"remaining_time":0.4288025887},
{"learn":[3.214962005],"iteration":880,"passed_time":3.146547322,"remaining_time":0.4250160401},
{"learn":[3.214081828],"iteration":881,"passed_time":3.147958902,"remaining_time":0.4211554993},
{"learn":[3.213358337],"iteration":882,"passed_time":3.149256718,"remaining_time":0.4172854315},
{"learn":[3.210850401],"iteration":883,"passed_time":3.150514037,"remaining_time":0.4134158691},
{"learn":[3.207810328],"iteration":884,"passed_time":3.1528504,"remaining_time":0.4096924249},
{"learn":[3.204935073],"iteration":885,"passed_time":3.154744428,"remaining_time":0.4059151973},
{"learn":[3.20280198],"iteration":886,"passed_time":3.156208219,"remaining_time":0.4020874056},
{"learn":[3.200663495],"iteration":887,"passed_time":3.157824068,"remaining_time":0.3982841167},
{"learn":[3.197301669],"iteration":888,"passed_time":3.159203596,"remaining_time":0.3944562421},
{"learn":[3.195666943],"iteration":889,"passed_time":3.162011625,"remaining_time":0.3908104255},
{"learn":[3.193886506],"iteration":890,"passed_time":3.163732534,"remaining_time":0.3870334974},
{"learn":[3.190601248],"iteration":891,"passed_time":3.165211006,"remaining_time":0.3832318259},
{"learn":[3.188983797],"iteration":892,"passed_time":3.16671304,"remaining_time":0.3794381806},
{"learn":[3.187365749],"iteration":893,"passed_time":3.168127475,"remaining_time":0.3756392755},
{"learn":[3.186160771],"iteration":894,"passed_time":3.170418674,"remaining_time":0.3719485595},
{"learn":[3.185358981],"iteration":895,"passed_time":3.171946196,"remaining_time":0.3681723263},
{"learn":[3.183832164],"iteration":896,"passed_time":3.173230397,"remaining_time":0.3643731671},
{"learn":[3.183106966],"iteration":897,"passed_time":3.174715299,"remaining_time":0.3606024059},
{"learn":[3.182838152],"iteration":898,"passed_time":3.176125127,"remaining_time":0.3568282956},
{"learn":[3.180835453],"iteration":899,"passed_time":3.177393407,"remaining_time":0.3530437119},
{"learn":[3.179957348],"iteration":900,"passed_time":3.179431672,"remaining_time":0.349349318},
{"learn":[3.179752966],"iteration":901,"passed_time":3.180913574,"remaining_time":0.3455981488},
{"learn":[3.178851983],"iteration":902,"passed_time":3.182242999,"remaining_time":0.3418356267},
{"learn":[3.176748586],"iteration":903,"passed_time":3.18344445,"remaining_time":0.3380648974},
{"learn":[3.172960988],"iteration":904,"passed_time":3.18470809,"remaining_time":0.3343063741},
{"learn":[3.172794225],"iteration":905,"passed_time":3.186018279,"remaining_time":0.3305581879},
{"learn":[3.169996507],"iteration":906,"passed_time":3.188028815,"remaining_time":0.3268871883},
{"learn":[3.16813015],"iteration":907,"passed_time":3.189679122,"remaining_time":0.3231833471},
{"learn":[3.166920871],"iteration":908,"passed_time":3.191911588,"remaining_time":0.3195423042},
{"learn":[3.16531606],"iteration":909,"passed_time":3.193237717,"remaining_time":0.3158147193},
{"learn":[3.162035247],"iteration":910,"passed_time":3.194483656,"remaining_time":0.3120845723},
{"learn":[3.16189467],"iteration":911,"passed_time":3.195867982,"remaining_time":0.3083732263},
{"learn":[3.161008416],"iteration":912,"passed_time":3.198006337,"remaining_time":0.3047388295},
{"learn":[3.160560787],"iteration":913,"passed_time":3.199324998,"remaining_time":0.3010305797},
{"learn":[3.160416261],"iteration":914,"passed_time":3.200534465,"remaining_time":0.2973174093},
{"learn":[3.15844291],"iteration":915,"passed_time":3.201837008,"remaining_time":0.2936182409},
{"learn":[3.155040501],"iteration":916,"passed_time":3.203085581,"remaining_time":0.2899194146},
{"learn":[3.154937548],"iteration":917,"passed_time":3.204508906,"remaining_time":0.2862415363},
{"learn":[3.153721161],"iteration":918,"passed_time":3.206626671,"remaining_time":0.2826297719},
{"learn":[3.153170511],"iteration":919,"passed_time":3.208248389,"remaining_time":0.2789781207},
{"learn":[3.153113601],"iteration":920,"passed_time":3.209521412,"remaining_time":0.275300968},
{"learn":[3.150607379],"iteration":921,"passed_time":3.210777126,"remaining_time":0.271627566},
{"learn":[3.148408359],"iteration":922,"passed_time":3.212013799,"remaining_time":0.2679578142},
{"learn":[3.147495728],"iteration":923,"passed_time":3.213261354,"remaining_time":0.2642942239},
{"learn":[3.146946235],"iteration":924,"passed_time":3.215104761,"remaining_time":0.2606841698},
{"learn":[3.14472738],"iteration":925,"passed_time":3.21659797,"remaining_time":0.2570499458},
{"learn":[3.144469477],"iteration":926,"passed_time":3.217786376,"remaining_time":0.2533963381},
{"learn":[3.142975516],"iteration":927,"passed_time":3.219559617,"remaining_time":0.2497934186},
{"learn":[3.14079113],"iteration":928,"passed_time":3.221018602,"remaining_time":0.2461704206},
{"learn":[3.138173032],"iteration":929,"passed_time":3.222405342,"remaining_time":0.2425466386},
{"learn":[3.136352813],"iteration":930,"passed_time":3.224825041,"remaining_time":0.2390042189},
{"learn":[3.133735004],"iteration":931,"passed_time":3.226357332,"remaining_time":0.235399462},
{"learn":[3.1319496],"iteration":932,"passed_time":3.227533292,"remaining_time":0.231773559},
{"learn":[3.129865343],"iteration":933,"passed_time":3.228745392,"remaining_time":0.228155456},
{"learn":[3.129830206],"iteration":934,"passed_time":3.229630344,"remaining_time":0.2245197565},
{"learn":[3.126676562],"iteration":935,"passed_time":3.230799337,"remaining_time":0.2209093564},
{"learn":[3.12645665],"iteration":936,"passed_time":3.232261232,"remaining_time":0.2173238608},
{"learn":[3.126378007],"iteration":937,"passed_time":3.234768328,"remaining_time":0.2138119791},
{"learn":[3.124621914],"iteration":938,"passed_time":3.236305016,"remaining_time":0.210239197},
{"learn":[3.123379018],"iteration":939,"passed_time":3.237833616,"remaining_time":0.2066702308},
{"learn":[3.123332451],"iteration":940,"passed_time":3.239165308,"remaining_time":0.2030932553},
{"learn":[3.122432444],"iteration":941,"passed_time":3.240543198,"remaining_time":0.1995238912},
{"learn":[3.121889006],"iteration":942,"passed_time":3.242717283,"remaining_time":0.1960073013},
{"learn":[3.121070914],"iteration":943,"passed_time":3.243981929,"remaining_time":0.1924396059},
{"learn":[3.118444705],"iteration":944,"passed_time":3.245198135,"remaining_time":0.1888739655},
{"learn":[3.116820458],"iteration":945,"passed_time":3.246385835,"remaining_time":0.185311665},
{"learn":[3.114971041],"iteration":946,"passed_time":3.24805101,"remaining_time":0.181781102},
{"learn":[3.114685138],"iteration":947,"passed_time":3.24946967,"remaining_time":0.1782409524},
{"learn":[3.113399363],"iteration":948,"passed_time":3.251644065,"remaining_time":0.1747458876},
{"learn":[3.110575399],"iteration":949,"passed_time":3.252819325,"remaining_time":0.1712010171},
{"learn":[3.110466553],"iteration":950,"passed_time":3.253921515,"remaining_time":0.1676573651},
{"learn":[3.108691641],"iteration":951,"passed_time":3.255075608,"remaining_time":0.1641214592},
{"learn":[3.107898017],"iteration":952,"passed_time":3.256215366,"remaining_time":0.1605898449},
{"learn":[3.105551729],"iteration":953,"passed_time":3.25736855,"remaining_time":0.1570638924},
{"learn":[3.104824945],"iteration":954,"passed_time":3.258539466,"remaining_time":0.1535437445},
{"learn":[3.103186704],"iteration":955,"passed_time":3.260477676,"remaining_time":0.1500638261},
{"learn":[3.102330655],"iteration":956,"passed_time":3.262297979,"remaining_time":0.1465818319},
{"learn":[3.102291298],"iteration":957,"passed_time":3.263470397,"remaining_time":0.1430749026},
{"learn":[3.100363529],"iteration":958,"passed_time":3.264663913,"remaining_time":0.1395737439},
{"learn":[3.097871596],"iteration":959,"passed_time":3.265886587,"remaining_time":0.1360786078},
{"learn":[3.097372213],"iteration":960,"passed_time":3.267276251,"remaining_time":0.1325949779},
{"learn":[3.095981813],"iteration":961,"passed_time":3.269140837,"remaining_time":0.1291344613},
{"learn":[3.095347452],"iteration":962,"passed_time":3.270600064,"remaining_time":0.1256616847},
{"learn":[3.094728409],"iteration":963,"passed_time":3.271798723,"remaining_time":0.1221833548},
{"learn":[3.094118537],"iteration":964,"passed_time":3.273004573,"remaining_time":0.1187100104},
{"learn":[3.093793695],"iteration":965,"passed_time":3.274108095,"remaining_time":0.115237759},
{"learn":[3.092581602],"iteration":966,"passed_time":3.278139718,"remaining_time":0.1118703317},
{"learn":[3.091694202],"iteration":967,"passed_time":3.279884135,"remaining_time":0.1084259218},
{"learn":[3.090298312],"iteration":968,"passed_time":3.281150057,"remaining_time":0.1049697129},
{"learn":[3.090020107],"iteration":969,"passed_time":3.282343957,"remaining_time":0.1015157925},
{"learn":[3.088949869],"iteration":970,"passed_time":3.283849194,"remaining_time":0.09807582555},
{"learn":[3.086700204],"iteration":971,"passed_time":3.285567628,"remaining_time":0.09464598106},
{"learn":[3.086584317],"iteration":972,"passed_time":3.288145743,"remaining_time":0.09124350983},
{"learn":[3.084850742],"iteration":973,"passed_time":3.29020175,"remaining_time":0.08782879416},
{"learn":[3.084239948],"iteration":974,"passed_time":3.291420439,"remaining_time":0.08439539588},
{"learn":[3.082561673],"iteration":975,"passed_time":3.292643133,"remaining_time":0.08096663442},
{"learn":[3.07991814],"iteration":976,"passed_time":3.293845152,"remaining_time":0.07754190225},
{"learn":[3.079350277],"iteration":977,"passed_time":3.295333528,"remaining_time":0.07412815708},
{"learn":[3.077637462],"iteration":978,"passed_time":3.297085185,"remaining_time":0.07072399273},
{"learn":[3.076733301],"iteration":979,"passed_time":3.298351398,"remaining_time":0.06731329385},
{"learn":[3.07594065],"iteration":980,"passed_time":3.299577098,"remaining_time":0.06390618233},
{"learn":[3.072594655],"iteration":981,"passed_time":3.300786961,"remaining_time":0.06050322332},
{"learn":[3.071977674],"iteration":982,"passed_time":3.302030685,"remaining_time":0.05710531195},
{"learn":[3.069532634],"iteration":983,"passed_time":3.304059593,"remaining_time":0.05372454623},
{"learn":[3.068870784],"iteration":984,"passed_time":3.305744,"remaining_time":0.05034127918},
{"learn":[3.068801463],"iteration":985,"passed_time":3.306971653,"remaining_time":0.04695497276},
{"learn":[3.067433249],"iteration":986,"passed_time":3.308179994,"remaining_time":0.04357278614},
{"learn":[3.065611456],"iteration":987,"passed_time":3.309432865,"remaining_time":0.04019554087},
{"learn":[3.063039162],"iteration":988,"passed_time":3.310615924,"remaining_time":0.03682181513},
{"learn":[3.06177873],"iteration":989,"passed_time":3.311937206,"remaining_time":0.03345391117},
{"learn":[3.061689148],"iteration":990,"passed_time":3.313767999,"remaining_time":0.03009476487},
{"learn":[3.058984039],"iteration":991,"passed_time":3.315098061,"remaining_time":0.02673466178},
{"learn":[3.057492984],"iteration":992,"passed_time":3.316385518,"remaining_time":0.02337834705},
{"learn":[3.057290731],"iteration":993,"passed_time":3.318002202,"remaining_time":0.0200281823},
{"learn":[3.056068348],"iteration":994,"passed_time":3.319130493,"remaining_time":0.0166790477},
{"learn":[3.054987307],"iteration":995,"passed_time":3.320300142,"remaining_time":0.01333453872},
{"learn":[3.054200234],"iteration":996,"passed_time":3.321855863,"remaining_time":0.009995554251},
{"learn":[3.052732869],"iteration":997,"passed_time":3.32371848,"remaining_time":0.006660758477},
{"learn":[3.051787862],"iteration":998,"passed_time":3.324928675,"remaining_time":0.003328256932},
{"learn":[3.051366222],"iteration":999,"passed_time":3.326061083,"remaining_time":0}
]}